<?xml version='1.0' encoding='UTF-8'?><m:StructureSpecificData xmlns:m="http://www.sdmx.org/resources/sdmxml/schemas/v3_0/message" xsi:schemaLocation="http://www.sdmx.org/resources/sdmxml/schemas/v3_0/message https://ec.europa.eu/eurostat/api/dissemination/sdmx/3.0/xsd/SDMXMessage.xsd" xmlns:s="http://www.sdmx.org/resources/sdmxml/schemas/v3_0/data/structurespecific" xmlns:u="urn:sdmx:org.sdmx.infomodel.datastructure.Dataflow=ESTAT:UNE_RT_Q(1.0):ObsLevelDim:TIME_PERIOD" xmlns:c="http://www.sdmx.org/resources/sdmxml/schemas/v3_0/common" xmlns:xsi="http://www.w3.org/2001/XMLSchema-instance"> <m:Header><m:ID>05376FF73773478C97A08D0627638F4C</m:ID><m:Test>false</m:Test><m:Prepared>2024-05-09T17:17:00.307Z</m:Prepared><m:Sender id="ESTAT"/><m:Structure dimensionAtObservation="TIME_PERIOD" namespace="urn:sdmx:org.sdmx.infomodel.datastructure.Dataflow=ESTAT:UNE_RT_Q(1.0):ObsLevelDim:TIME_PERIOD" structureID="STR1"><c:StructureUsage>urn:sdmx:org.sdmx.infomodel.datastructure.Dataflow=ESTAT:UNE_RT_Q(1.0)</c:StructureUsage></m:Structure><m:DataSetID>UNE_RT_Q</m:DataSetID><m:Extracted>2024-05-09T17:17:00.307Z</m:Extracted></m:Header><m:DataSet s:structureRef="STR1" xsi:type="s:DataSetType"><Series age="Y15-74" freq="Q" geo="AT" sex="T" s_adj="SA" unit="PC_ACT"><Obs TIME_PERIOD="2010-Q1" OBS_VALUE="5.4"/><Obs TIME_PERIOD="2010-Q2" OBS_VALUE="5.4"/><Obs TIME_PERIOD="2010-Q3" OBS_VALUE="5.1"/><Obs TIME_PERIOD="2010-Q4" OBS_VALUE="4.9"/><Obs TIME_PERIOD="2011-Q1" OBS_VALUE="5.2"/><Obs TIME_PERIOD="2011-Q2" OBS_VALUE="4.8"/><Obs TIME_PERIOD="2011-Q3" OBS_VALUE="4.3"/><Obs TIME_PERIOD="2011-Q4" OBS_VALUE="5.2"/><Obs TIME_PERIOD="2012-Q1" OBS_VALUE="4.9"/><Obs TIME_PERIOD="2012-Q2" OBS_VALUE="5.2"/><Obs TIME_PERIOD="2012-Q3" OBS_VALUE="5.4"/><Obs TIME_PERIOD="2012-Q4" OBS_VALUE="5.3"/><Obs TIME_PERIOD="2013-Q1" OBS_VALUE="5.9"/><Obs TIME_PERIOD="2013-Q2" OBS_VALUE="5.5"/><Obs TIME_PERIOD="2013-Q3" OBS_VALUE="5.7"/><Obs TIME_PERIOD="2013-Q4" OBS_VALUE="5.9"/><Obs TIME_PERIOD="2014-Q1" OBS_VALUE="6.1"/><Obs TIME_PERIOD="2014-Q2" OBS_VALUE="6.0"/><Obs TIME_PERIOD="2014-Q3" OBS_VALUE="6.0"/><Obs TIME_PERIOD="2014-Q4" OBS_VALUE="6.1"/><Obs TIME_PERIOD="2015-Q1" OBS_VALUE="6.0"/><Obs TIME_PERIOD="2015-Q2" OBS_VALUE="6.3"/><Obs TIME_PERIOD="2015-Q3" OBS_VALUE="6.1"/><Obs TIME_PERIOD="2015-Q4" OBS_VALUE="6.3"/><Obs TIME_PERIOD="2016-Q1" OBS_VALUE="6.4"/><Obs TIME_PERIOD="2016-Q2" OBS_VALUE="6.6"/><Obs TIME_PERIOD="2016-Q3" OBS_VALUE="6.6"/><Obs TIME_PERIOD="2016-Q4" OBS_VALUE="6.2"/><Obs TIME_PERIOD="2017-Q1" OBS_VALUE="6.1"/><Obs TIME_PERIOD="2017-Q2" OBS_VALUE="5.9"/><Obs TIME_PERIOD="2017-Q3" OBS_VALUE="5.9"/><Obs TIME_PERIOD="2017-Q4" OBS_VALUE="5.8"/><Obs TIME_PERIOD="2018-Q1" OBS_VALUE="5.4"/><Obs TIME_PERIOD="2018-Q2" OBS_VALUE="5.0"/><Obs TIME_PERIOD="2018-Q3" OBS_VALUE="5.3"/><Obs TIME_PERIOD="2018-Q4" OBS_VALUE="5.1"/><Obs TIME_PERIOD="2019-Q1" OBS_VALUE="5.1"/><Obs TIME_PERIOD="2019-Q2" OBS_VALUE="4.8"/><Obs TIME_PERIOD="2019-Q3" OBS_VALUE="4.8"/><Obs TIME_PERIOD="2019-Q4" OBS_VALUE="4.6"/><Obs TIME_PERIOD="2020-Q1" OBS_VALUE="4.7"/><Obs TIME_PERIOD="2020-Q2" OBS_VALUE="7.0"/><Obs TIME_PERIOD="2020-Q3" OBS_VALUE="6.4"/><Obs TIME_PERIOD="2020-Q4" OBS_VALUE="6.3"/><Obs TIME_PERIOD="2021-Q1" OBS_VALUE="7.1"/><Obs TIME_PERIOD="2021-Q2" OBS_VALUE="6.7"/><Obs TIME_PERIOD="2021-Q3" OBS_VALUE="5.5"/><Obs TIME_PERIOD="2021-Q4" OBS_VALUE="5.3"/><Obs TIME_PERIOD="2022-Q1" OBS_VALUE="4.7"/><Obs TIME_PERIOD="2022-Q2" OBS_VALUE="4.4"/><Obs TIME_PERIOD="2022-Q3" OBS_VALUE="4.9"/><Obs TIME_PERIOD="2022-Q4" OBS_VALUE="5.0"/><Obs TIME_PERIOD="2023-Q1" OBS_VALUE="4.9"/><Obs TIME_PERIOD="2023-Q2" OBS_VALUE="5.0"/><Obs TIME_PERIOD="2023-Q3" OBS_VALUE="5.4"/><Obs TIME_PERIOD="2023-Q4" OBS_VALUE="5.2"/></Series><Series age="Y15-74" freq="Q" geo="BA" sex="T" s_adj="SA" unit="PC_ACT"><Obs TIME_PERIOD="2021-Q1" OBS_VALUE="19.0"/><Obs TIME_PERIOD="2021-Q2" OBS_VALUE="18.1"/><Obs TIME_PERIOD="2021-Q3" OBS_VALUE="16.4"/><Obs TIME_PERIOD="2021-Q4" OBS_VALUE="16.1"/><Obs TIME_PERIOD="2022-Q1" OBS_VALUE="16.7"/><Obs TIME_PERIOD="2022-Q2" OBS_VALUE="15.7"/><Obs TIME_PERIOD="2022-Q3" OBS_VALUE="14.8"/><Obs TIME_PERIOD="2022-Q4" OBS_VALUE="14.3"/><Obs TIME_PERIOD="2023-Q1" OBS_VALUE="13.3"/><Obs TIME_PERIOD="2023-Q2" OBS_VALUE="13.1"/><Obs TIME_PERIOD="2023-Q3" OBS_VALUE="13.6"/><Obs TIME_PERIOD="2023-Q4" OBS_VALUE="12.7"/></Series><Series age="Y15-74" freq="Q" geo="BE" sex="T" s_adj="SA" unit="PC_ACT"><Obs TIME_PERIOD="2010-Q1" OBS_VALUE="8.7"/><Obs TIME_PERIOD="2010-Q2" OBS_VALUE="8.3"/><Obs TIME_PERIOD="2010-Q3" OBS_VALUE="8.6"/><Obs TIME_PERIOD="2010-Q4" OBS_VALUE="7.9"/><Obs TIME_PERIOD="2011-Q1" OBS_VALUE="7.2"/><Obs TIME_PERIOD="2011-Q2" OBS_VALUE="6.8"/><Obs TIME_PERIOD="2011-Q3" OBS_VALUE="7.6"/><Obs TIME_PERIOD="2011-Q4" OBS_VALUE="7.2"/><Obs TIME_PERIOD="2012-Q1" OBS_VALUE="7.4"/><Obs TIME_PERIOD="2012-Q2" OBS_VALUE="7.2"/><Obs TIME_PERIOD="2012-Q3" OBS_VALUE="7.7"/><Obs TIME_PERIOD="2012-Q4" OBS_VALUE="8.3"/><Obs TIME_PERIOD="2013-Q1" OBS_VALUE="8.6"/><Obs TIME_PERIOD="2013-Q2" OBS_VALUE="8.4"/><Obs TIME_PERIOD="2013-Q3" OBS_VALUE="8.6"/><Obs TIME_PERIOD="2013-Q4" OBS_VALUE="8.6"/><Obs TIME_PERIOD="2014-Q1" OBS_VALUE="8.8"/><Obs TIME_PERIOD="2014-Q2" OBS_VALUE="8.4"/><Obs TIME_PERIOD="2014-Q3" OBS_VALUE="8.7"/><Obs TIME_PERIOD="2014-Q4" OBS_VALUE="8.7"/><Obs TIME_PERIOD="2015-Q1" OBS_VALUE="9.0"/><Obs TIME_PERIOD="2015-Q2" OBS_VALUE="8.6"/><Obs TIME_PERIOD="2015-Q3" OBS_VALUE="8.3"/><Obs TIME_PERIOD="2015-Q4" OBS_VALUE="8.8"/><Obs TIME_PERIOD="2016-Q1" OBS_VALUE="8.5"/><Obs TIME_PERIOD="2016-Q2" OBS_VALUE="8.1"/><Obs TIME_PERIOD="2016-Q3" OBS_VALUE="7.8"/><Obs TIME_PERIOD="2016-Q4" OBS_VALUE="7.3"/><Obs TIME_PERIOD="2017-Q1" OBS_VALUE="7.9" OBS_FLAG="b"/><Obs TIME_PERIOD="2017-Q2" OBS_VALUE="7.2"/><Obs TIME_PERIOD="2017-Q3" OBS_VALUE="7.2"/><Obs TIME_PERIOD="2017-Q4" OBS_VALUE="6.4"/><Obs TIME_PERIOD="2018-Q1" OBS_VALUE="6.2"/><Obs TIME_PERIOD="2018-Q2" OBS_VALUE="6.2"/><Obs TIME_PERIOD="2018-Q3" OBS_VALUE="5.8"/><Obs TIME_PERIOD="2018-Q4" OBS_VALUE="5.8"/><Obs TIME_PERIOD="2019-Q1" OBS_VALUE="5.8"/><Obs TIME_PERIOD="2019-Q2" OBS_VALUE="5.4"/><Obs TIME_PERIOD="2019-Q3" OBS_VALUE="5.3"/><Obs TIME_PERIOD="2019-Q4" OBS_VALUE="5.3"/><Obs TIME_PERIOD="2020-Q1" OBS_VALUE="5.2"/><Obs TIME_PERIOD="2020-Q2" OBS_VALUE="5.3"/><Obs TIME_PERIOD="2020-Q3" OBS_VALUE="6.5"/><Obs TIME_PERIOD="2020-Q4" OBS_VALUE="6.0"/><Obs TIME_PERIOD="2021-Q1" OBS_VALUE="6.8"/><Obs TIME_PERIOD="2021-Q2" OBS_VALUE="6.2"/><Obs TIME_PERIOD="2021-Q3" OBS_VALUE="6.4"/><Obs TIME_PERIOD="2021-Q4" OBS_VALUE="5.8"/><Obs TIME_PERIOD="2022-Q1" OBS_VALUE="5.4"/><Obs TIME_PERIOD="2022-Q2" OBS_VALUE="5.7"/><Obs TIME_PERIOD="2022-Q3" OBS_VALUE="5.5"/><Obs TIME_PERIOD="2022-Q4" OBS_VALUE="5.7"/><Obs TIME_PERIOD="2023-Q1" OBS_VALUE="5.7"/><Obs TIME_PERIOD="2023-Q2" OBS_VALUE="5.5"/><Obs TIME_PERIOD="2023-Q3" OBS_VALUE="5.4"/><Obs TIME_PERIOD="2023-Q4" OBS_VALUE="5.5"/></Series><Series age="Y15-74" freq="Q" geo="BG" sex="T" s_adj="SA" unit="PC_ACT"><Obs TIME_PERIOD="2010-Q1" OBS_VALUE="10.3" OBS_FLAG="b"/><Obs TIME_PERIOD="2010-Q2" OBS_VALUE="11.1"/><Obs TIME_PERIOD="2010-Q3" OBS_VALUE="11.5"/><Obs TIME_PERIOD="2010-Q4" OBS_VALUE="12.3"/><Obs TIME_PERIOD="2011-Q1" OBS_VALUE="12.1" OBS_FLAG="b"/><Obs TIME_PERIOD="2011-Q2" OBS_VALUE="12.3"/><Obs TIME_PERIOD="2011-Q3" OBS_VALUE="12.3"/><Obs TIME_PERIOD="2011-Q4" OBS_VALUE="12.6"/><Obs TIME_PERIOD="2012-Q1" OBS_VALUE="12.9"/><Obs TIME_PERIOD="2012-Q2" OBS_VALUE="13.2"/><Obs TIME_PERIOD="2012-Q3" OBS_VALUE="13.4"/><Obs TIME_PERIOD="2012-Q4" OBS_VALUE="13.6"/><Obs TIME_PERIOD="2013-Q1" OBS_VALUE="13.9"/><Obs TIME_PERIOD="2013-Q2" OBS_VALUE="13.9"/><Obs TIME_PERIOD="2013-Q3" OBS_VALUE="13.7"/><Obs TIME_PERIOD="2013-Q4" OBS_VALUE="14.0"/><Obs TIME_PERIOD="2014-Q1" OBS_VALUE="13.2"/><Obs TIME_PERIOD="2014-Q2" OBS_VALUE="12.3"/><Obs TIME_PERIOD="2014-Q3" OBS_VALUE="12.4"/><Obs TIME_PERIOD="2014-Q4" OBS_VALUE="11.7"/><Obs TIME_PERIOD="2015-Q1" OBS_VALUE="10.9"/><Obs TIME_PERIOD="2015-Q2" OBS_VALUE="10.6"/><Obs TIME_PERIOD="2015-Q3" OBS_VALUE="9.8"/><Obs TIME_PERIOD="2015-Q4" OBS_VALUE="9.2"/><Obs TIME_PERIOD="2016-Q1" OBS_VALUE="9.1"/><Obs TIME_PERIOD="2016-Q2" OBS_VALUE="8.7"/><Obs TIME_PERIOD="2016-Q3" OBS_VALUE="8.4"/><Obs TIME_PERIOD="2016-Q4" OBS_VALUE="8.0"/><Obs TIME_PERIOD="2017-Q1" OBS_VALUE="7.5"/><Obs TIME_PERIOD="2017-Q2" OBS_VALUE="7.1"/><Obs TIME_PERIOD="2017-Q3" OBS_VALUE="7.1"/><Obs TIME_PERIOD="2017-Q4" OBS_VALUE="6.8"/><Obs TIME_PERIOD="2018-Q1" OBS_VALUE="6.5"/><Obs TIME_PERIOD="2018-Q2" OBS_VALUE="6.4"/><Obs TIME_PERIOD="2018-Q3" OBS_VALUE="6.2"/><Obs TIME_PERIOD="2018-Q4" OBS_VALUE="5.7"/><Obs TIME_PERIOD="2019-Q1" OBS_VALUE="5.6"/><Obs TIME_PERIOD="2019-Q2" OBS_VALUE="5.1"/><Obs TIME_PERIOD="2019-Q3" OBS_VALUE="5.0"/><Obs TIME_PERIOD="2019-Q4" OBS_VALUE="5.2"/><Obs TIME_PERIOD="2020-Q1" OBS_VALUE="5.2"/><Obs TIME_PERIOD="2020-Q2" OBS_VALUE="6.6"/><Obs TIME_PERIOD="2020-Q3" OBS_VALUE="6.2"/><Obs TIME_PERIOD="2020-Q4" OBS_VALUE="6.3"/><Obs TIME_PERIOD="2021-Q1" OBS_VALUE="5.9"/><Obs TIME_PERIOD="2021-Q2" OBS_VALUE="5.4"/><Obs TIME_PERIOD="2021-Q3" OBS_VALUE="5.0"/><Obs TIME_PERIOD="2021-Q4" OBS_VALUE="4.8"/><Obs TIME_PERIOD="2022-Q1" OBS_VALUE="4.4" OBS_FLAG="b"/><Obs TIME_PERIOD="2022-Q2" OBS_VALUE="4.3"/><Obs TIME_PERIOD="2022-Q3" OBS_VALUE="4.0"/><Obs TIME_PERIOD="2022-Q4" OBS_VALUE="4.0"/><Obs TIME_PERIOD="2023-Q1" OBS_VALUE="4.1"/><Obs TIME_PERIOD="2023-Q2" OBS_VALUE="4.3"/><Obs TIME_PERIOD="2023-Q3" OBS_VALUE="4.4"/><Obs TIME_PERIOD="2023-Q4" OBS_VALUE="4.5"/></Series><Series age="Y15-74" freq="Q" geo="CH" sex="T" s_adj="SA" unit="PC_ACT"><Obs TIME_PERIOD="2010-Q1" OBS_VALUE="5.1" OBS_FLAG="b"/><Obs TIME_PERIOD="2010-Q2" OBS_VALUE="5.0"/><Obs TIME_PERIOD="2010-Q3" OBS_VALUE="4.7"/><Obs TIME_PERIOD="2010-Q4" OBS_VALUE="4.5"/><Obs TIME_PERIOD="2011-Q1" OBS_VALUE="4.4"/><Obs TIME_PERIOD="2011-Q2" OBS_VALUE="4.3"/><Obs TIME_PERIOD="2011-Q3" OBS_VALUE="4.4"/><Obs TIME_PERIOD="2011-Q4" OBS_VALUE="4.6"/><Obs TIME_PERIOD="2012-Q1" OBS_VALUE="4.3"/><Obs TIME_PERIOD="2012-Q2" OBS_VALUE="4.4"/><Obs TIME_PERIOD="2012-Q3" OBS_VALUE="4.5"/><Obs TIME_PERIOD="2012-Q4" OBS_VALUE="4.9"/><Obs TIME_PERIOD="2013-Q1" OBS_VALUE="4.9"/><Obs TIME_PERIOD="2013-Q2" OBS_VALUE="4.8"/><Obs TIME_PERIOD="2013-Q3" OBS_VALUE="4.7"/><Obs TIME_PERIOD="2013-Q4" OBS_VALUE="4.7"/><Obs TIME_PERIOD="2014-Q1" OBS_VALUE="5.0"/><Obs TIME_PERIOD="2014-Q2" OBS_VALUE="5.0"/><Obs TIME_PERIOD="2014-Q3" OBS_VALUE="4.9"/><Obs TIME_PERIOD="2014-Q4" OBS_VALUE="4.5"/><Obs TIME_PERIOD="2015-Q1" OBS_VALUE="4.5"/><Obs TIME_PERIOD="2015-Q2" OBS_VALUE="4.7"/><Obs TIME_PERIOD="2015-Q3" OBS_VALUE="5.0"/><Obs TIME_PERIOD="2015-Q4" OBS_VALUE="5.1"/><Obs TIME_PERIOD="2016-Q1" OBS_VALUE="5.1"/><Obs TIME_PERIOD="2016-Q2" OBS_VALUE="4.9"/><Obs TIME_PERIOD="2016-Q3" OBS_VALUE="5.0"/><Obs TIME_PERIOD="2016-Q4" OBS_VALUE="4.8"/><Obs TIME_PERIOD="2017-Q1" OBS_VALUE="5.0"/><Obs TIME_PERIOD="2017-Q2" OBS_VALUE="4.7"/><Obs TIME_PERIOD="2017-Q3" OBS_VALUE="4.9"/><Obs TIME_PERIOD="2017-Q4" OBS_VALUE="4.8"/><Obs TIME_PERIOD="2018-Q1" OBS_VALUE="4.9"/><Obs TIME_PERIOD="2018-Q2" OBS_VALUE="4.9"/><Obs TIME_PERIOD="2018-Q3" OBS_VALUE="4.3"/><Obs TIME_PERIOD="2018-Q4" OBS_VALUE="4.8"/><Obs TIME_PERIOD="2019-Q1" OBS_VALUE="4.6"/><Obs TIME_PERIOD="2019-Q2" OBS_VALUE="4.4"/><Obs TIME_PERIOD="2019-Q3" OBS_VALUE="4.5"/><Obs TIME_PERIOD="2019-Q4" OBS_VALUE="4.1"/><Obs TIME_PERIOD="2020-Q1" OBS_VALUE="4.2"/><Obs TIME_PERIOD="2020-Q2" OBS_VALUE="4.9"/><Obs TIME_PERIOD="2020-Q3" OBS_VALUE="5.2"/><Obs TIME_PERIOD="2020-Q4" OBS_VALUE="5.2"/><Obs TIME_PERIOD="2021-Q1" OBS_VALUE="5.5"/><Obs TIME_PERIOD="2021-Q2" OBS_VALUE="5.3"/><Obs TIME_PERIOD="2021-Q3" OBS_VALUE="5.0"/><Obs TIME_PERIOD="2021-Q4" OBS_VALUE="4.7"/><Obs TIME_PERIOD="2022-Q1" OBS_VALUE="4.3"/><Obs TIME_PERIOD="2022-Q2" OBS_VALUE="4.4"/><Obs TIME_PERIOD="2022-Q3" OBS_VALUE="4.2"/><Obs TIME_PERIOD="2022-Q4" OBS_VALUE="4.4"/><Obs TIME_PERIOD="2023-Q1" OBS_VALUE="4.1"/><Obs TIME_PERIOD="2023-Q2" OBS_VALUE="4.0"/><Obs TIME_PERIOD="2023-Q3" OBS_VALUE="4.1"/><Obs TIME_PERIOD="2023-Q4" OBS_VALUE="4.1"/></Series><Series age="Y15-74" freq="Q" geo="CY" sex="T" s_adj="SA" unit="PC_ACT"><Obs TIME_PERIOD="2010-Q1" OBS_VALUE="6.9"/><Obs TIME_PERIOD="2010-Q2" OBS_VALUE="6.5"/><Obs TIME_PERIOD="2010-Q3" OBS_VALUE="6.0"/><Obs TIME_PERIOD="2010-Q4" OBS_VALUE="5.9"/><Obs TIME_PERIOD="2011-Q1" OBS_VALUE="6.9"/><Obs TIME_PERIOD="2011-Q2" OBS_VALUE="7.3"/><Obs TIME_PERIOD="2011-Q3" OBS_VALUE="8.0"/><Obs TIME_PERIOD="2011-Q4" OBS_VALUE="9.5"/><Obs TIME_PERIOD="2012-Q1" OBS_VALUE="10.5"/><Obs TIME_PERIOD="2012-Q2" OBS_VALUE="11.4"/><Obs TIME_PERIOD="2012-Q3" OBS_VALUE="12.2"/><Obs TIME_PERIOD="2012-Q4" OBS_VALUE="13.4"/><Obs TIME_PERIOD="2013-Q1" OBS_VALUE="15.1"/><Obs TIME_PERIOD="2013-Q2" OBS_VALUE="15.7"/><Obs TIME_PERIOD="2013-Q3" OBS_VALUE="16.2"/><Obs TIME_PERIOD="2013-Q4" OBS_VALUE="16.5"/><Obs TIME_PERIOD="2014-Q1" OBS_VALUE="16.2"/><Obs TIME_PERIOD="2014-Q2" OBS_VALUE="16.1"/><Obs TIME_PERIOD="2014-Q3" OBS_VALUE="16.1"/><Obs TIME_PERIOD="2014-Q4" OBS_VALUE="16.4"/><Obs TIME_PERIOD="2015-Q1" OBS_VALUE="16.5"/><Obs TIME_PERIOD="2015-Q2" OBS_VALUE="15.2"/><Obs TIME_PERIOD="2015-Q3" OBS_VALUE="14.7"/><Obs TIME_PERIOD="2015-Q4" OBS_VALUE="13.2"/><Obs TIME_PERIOD="2016-Q1" OBS_VALUE="13.0"/><Obs TIME_PERIOD="2016-Q2" OBS_VALUE="12.8"/><Obs TIME_PERIOD="2016-Q3" OBS_VALUE="13.1"/><Obs TIME_PERIOD="2016-Q4" OBS_VALUE="13.0"/><Obs TIME_PERIOD="2017-Q1" OBS_VALUE="12.4"/><Obs TIME_PERIOD="2017-Q2" OBS_VALUE="11.4"/><Obs TIME_PERIOD="2017-Q3" OBS_VALUE="10.4"/><Obs TIME_PERIOD="2017-Q4" OBS_VALUE="10.3"/><Obs TIME_PERIOD="2018-Q1" OBS_VALUE="9.6"/><Obs TIME_PERIOD="2018-Q2" OBS_VALUE="8.1"/><Obs TIME_PERIOD="2018-Q3" OBS_VALUE="8.1"/><Obs TIME_PERIOD="2018-Q4" OBS_VALUE="7.8"/><Obs TIME_PERIOD="2019-Q1" OBS_VALUE="7.8"/><Obs TIME_PERIOD="2019-Q2" OBS_VALUE="7.0"/><Obs TIME_PERIOD="2019-Q3" OBS_VALUE="6.7"/><Obs TIME_PERIOD="2019-Q4" OBS_VALUE="6.7"/><Obs TIME_PERIOD="2020-Q1" OBS_VALUE="6.8"/><Obs TIME_PERIOD="2020-Q2" OBS_VALUE="7.1"/><Obs TIME_PERIOD="2020-Q3" OBS_VALUE="8.2"/><Obs TIME_PERIOD="2020-Q4" OBS_VALUE="8.3"/><Obs TIME_PERIOD="2021-Q1" OBS_VALUE="8.3"/><Obs TIME_PERIOD="2021-Q2" OBS_VALUE="8.3"/><Obs TIME_PERIOD="2021-Q3" OBS_VALUE="6.8"/><Obs TIME_PERIOD="2021-Q4" OBS_VALUE="6.6"/><Obs TIME_PERIOD="2022-Q1" OBS_VALUE="6.5"/><Obs TIME_PERIOD="2022-Q2" OBS_VALUE="6.7"/><Obs TIME_PERIOD="2022-Q3" OBS_VALUE="6.9"/><Obs TIME_PERIOD="2022-Q4" OBS_VALUE="7.0"/><Obs TIME_PERIOD="2023-Q1" OBS_VALUE="6.5"/><Obs TIME_PERIOD="2023-Q2" OBS_VALUE="6.0"/><Obs TIME_PERIOD="2023-Q3" OBS_VALUE="6.0"/><Obs TIME_PERIOD="2023-Q4" OBS_VALUE="6.0"/></Series><Series age="Y15-74" freq="Q" geo="CZ" sex="T" s_adj="SA" unit="PC_ACT"><Obs TIME_PERIOD="2010-Q1" OBS_VALUE="7.8"/><Obs TIME_PERIOD="2010-Q2" OBS_VALUE="7.3"/><Obs TIME_PERIOD="2010-Q3" OBS_VALUE="7.1"/><Obs TIME_PERIOD="2010-Q4" OBS_VALUE="7.0"/><Obs TIME_PERIOD="2011-Q1" OBS_VALUE="6.9" OBS_FLAG="b"/><Obs TIME_PERIOD="2011-Q2" OBS_VALUE="6.9"/><Obs TIME_PERIOD="2011-Q3" OBS_VALUE="6.6"/><Obs TIME_PERIOD="2011-Q4" OBS_VALUE="6.5"/><Obs TIME_PERIOD="2012-Q1" OBS_VALUE="6.8"/><Obs TIME_PERIOD="2012-Q2" OBS_VALUE="6.9"/><Obs TIME_PERIOD="2012-Q3" OBS_VALUE="7.0"/><Obs TIME_PERIOD="2012-Q4" OBS_VALUE="7.3"/><Obs TIME_PERIOD="2013-Q1" OBS_VALUE="7.2"/><Obs TIME_PERIOD="2013-Q2" OBS_VALUE="6.9"/><Obs TIME_PERIOD="2013-Q3" OBS_VALUE="7.0"/><Obs TIME_PERIOD="2013-Q4" OBS_VALUE="6.8"/><Obs TIME_PERIOD="2014-Q1" OBS_VALUE="6.5"/><Obs TIME_PERIOD="2014-Q2" OBS_VALUE="6.2"/><Obs TIME_PERIOD="2014-Q3" OBS_VALUE="5.9"/><Obs TIME_PERIOD="2014-Q4" OBS_VALUE="5.8"/><Obs TIME_PERIOD="2015-Q1" OBS_VALUE="5.7"/><Obs TIME_PERIOD="2015-Q2" OBS_VALUE="5.1"/><Obs TIME_PERIOD="2015-Q3" OBS_VALUE="4.8"/><Obs TIME_PERIOD="2015-Q4" OBS_VALUE="4.5"/><Obs TIME_PERIOD="2016-Q1" OBS_VALUE="4.2"/><Obs TIME_PERIOD="2016-Q2" OBS_VALUE="4.1"/><Obs TIME_PERIOD="2016-Q3" OBS_VALUE="3.9"/><Obs TIME_PERIOD="2016-Q4" OBS_VALUE="3.6"/><Obs TIME_PERIOD="2017-Q1" OBS_VALUE="3.3"/><Obs TIME_PERIOD="2017-Q2" OBS_VALUE="3.1"/><Obs TIME_PERIOD="2017-Q3" OBS_VALUE="2.7"/><Obs TIME_PERIOD="2017-Q4" OBS_VALUE="2.4"/><Obs TIME_PERIOD="2018-Q1" OBS_VALUE="2.4"/><Obs TIME_PERIOD="2018-Q2" OBS_VALUE="2.3"/><Obs TIME_PERIOD="2018-Q3" OBS_VALUE="2.3"/><Obs TIME_PERIOD="2018-Q4" OBS_VALUE="2.1"/><Obs TIME_PERIOD="2019-Q1" OBS_VALUE="2.0"/><Obs TIME_PERIOD="2019-Q2" OBS_VALUE="2.0"/><Obs TIME_PERIOD="2019-Q3" OBS_VALUE="2.0"/><Obs TIME_PERIOD="2019-Q4" OBS_VALUE="2.1"/><Obs TIME_PERIOD="2020-Q1" OBS_VALUE="2.0"/><Obs TIME_PERIOD="2020-Q2" OBS_VALUE="2.5"/><Obs TIME_PERIOD="2020-Q3" OBS_VALUE="2.8"/><Obs TIME_PERIOD="2020-Q4" OBS_VALUE="3.1"/><Obs TIME_PERIOD="2021-Q1" OBS_VALUE="3.3"/><Obs TIME_PERIOD="2021-Q2" OBS_VALUE="3.0"/><Obs TIME_PERIOD="2021-Q3" OBS_VALUE="2.7"/><Obs TIME_PERIOD="2021-Q4" OBS_VALUE="2.3"/><Obs TIME_PERIOD="2022-Q1" OBS_VALUE="2.2"/><Obs TIME_PERIOD="2022-Q2" OBS_VALUE="2.2"/><Obs TIME_PERIOD="2022-Q3" OBS_VALUE="2.2"/><Obs TIME_PERIOD="2022-Q4" OBS_VALUE="2.3"/><Obs TIME_PERIOD="2023-Q1" OBS_VALUE="2.5"/><Obs TIME_PERIOD="2023-Q2" OBS_VALUE="2.6"/><Obs TIME_PERIOD="2023-Q3" OBS_VALUE="2.6"/><Obs TIME_PERIOD="2023-Q4" OBS_VALUE="2.6"/></Series><Series age="Y15-74" freq="Q" geo="DE" sex="T" s_adj="SA" unit="PC_ACT"><Obs TIME_PERIOD="2010-Q1" OBS_VALUE="7.1" OBS_FLAG="b"/><Obs TIME_PERIOD="2010-Q2" OBS_VALUE="6.6"/><Obs TIME_PERIOD="2010-Q3" OBS_VALUE="6.3"/><Obs TIME_PERIOD="2010-Q4" OBS_VALUE="6.3"/><Obs TIME_PERIOD="2011-Q1" OBS_VALUE="5.9" OBS_FLAG="b"/><Obs TIME_PERIOD="2011-Q2" OBS_VALUE="5.5"/><Obs TIME_PERIOD="2011-Q3" OBS_VALUE="5.4"/><Obs TIME_PERIOD="2011-Q4" OBS_VALUE="5.2"/><Obs TIME_PERIOD="2012-Q1" OBS_VALUE="5.2"/><Obs TIME_PERIOD="2012-Q2" OBS_VALUE="5.1"/><Obs TIME_PERIOD="2012-Q3" OBS_VALUE="5.1"/><Obs TIME_PERIOD="2012-Q4" OBS_VALUE="5.0"/><Obs TIME_PERIOD="2013-Q1" OBS_VALUE="5.1"/><Obs TIME_PERIOD="2013-Q2" OBS_VALUE="5.0"/><Obs TIME_PERIOD="2013-Q3" OBS_VALUE="4.8"/><Obs TIME_PERIOD="2013-Q4" OBS_VALUE="4.9"/><Obs TIME_PERIOD="2014-Q1" OBS_VALUE="4.9"/><Obs TIME_PERIOD="2014-Q2" OBS_VALUE="4.7"/><Obs TIME_PERIOD="2014-Q3" OBS_VALUE="4.6"/><Obs TIME_PERIOD="2014-Q4" OBS_VALUE="4.7"/><Obs TIME_PERIOD="2015-Q1" OBS_VALUE="4.5"/><Obs TIME_PERIOD="2015-Q2" OBS_VALUE="4.4"/><Obs TIME_PERIOD="2015-Q3" OBS_VALUE="4.2"/><Obs TIME_PERIOD="2015-Q4" OBS_VALUE="4.4"/><Obs TIME_PERIOD="2016-Q1" OBS_VALUE="4.1"/><Obs TIME_PERIOD="2016-Q2" OBS_VALUE="4.0"/><Obs TIME_PERIOD="2016-Q3" OBS_VALUE="3.9"/><Obs TIME_PERIOD="2016-Q4" OBS_VALUE="3.7"/><Obs TIME_PERIOD="2017-Q1" OBS_VALUE="3.7"/><Obs TIME_PERIOD="2017-Q2" OBS_VALUE="3.6"/><Obs TIME_PERIOD="2017-Q3" OBS_VALUE="3.5"/><Obs TIME_PERIOD="2017-Q4" OBS_VALUE="3.4"/><Obs TIME_PERIOD="2018-Q1" OBS_VALUE="3.3"/><Obs TIME_PERIOD="2018-Q2" OBS_VALUE="3.3"/><Obs TIME_PERIOD="2018-Q3" OBS_VALUE="3.2"/><Obs TIME_PERIOD="2018-Q4" OBS_VALUE="3.1"/><Obs TIME_PERIOD="2019-Q1" OBS_VALUE="3.0"/><Obs TIME_PERIOD="2019-Q2" OBS_VALUE="2.9"/><Obs TIME_PERIOD="2019-Q3" OBS_VALUE="3.0"/><Obs TIME_PERIOD="2019-Q4" OBS_VALUE="3.0"/><Obs TIME_PERIOD="2020-Q1" OBS_VALUE="3.3" OBS_FLAG="bu"/><Obs TIME_PERIOD="2020-Q2" OBS_VALUE="3.7" OBS_FLAG="u"/><Obs TIME_PERIOD="2020-Q3" OBS_VALUE="4.0" OBS_FLAG="u"/><Obs TIME_PERIOD="2020-Q4" OBS_VALUE="3.7" OBS_FLAG="u"/><Obs TIME_PERIOD="2021-Q1" OBS_VALUE="4.0"/><Obs TIME_PERIOD="2021-Q2" OBS_VALUE="3.8"/><Obs TIME_PERIOD="2021-Q3" OBS_VALUE="3.4"/><Obs TIME_PERIOD="2021-Q4" OBS_VALUE="3.4"/><Obs TIME_PERIOD="2022-Q1" OBS_VALUE="3.1"/><Obs TIME_PERIOD="2022-Q2" OBS_VALUE="3.2"/><Obs TIME_PERIOD="2022-Q3" OBS_VALUE="3.2"/><Obs TIME_PERIOD="2022-Q4" OBS_VALUE="3.1"/><Obs TIME_PERIOD="2023-Q1" OBS_VALUE="3.0"/><Obs TIME_PERIOD="2023-Q2" OBS_VALUE="3.1"/><Obs TIME_PERIOD="2023-Q3" OBS_VALUE="3.1"/><Obs TIME_PERIOD="2023-Q4" OBS_VALUE="3.1"/></Series><Series age="Y15-74" freq="Q" geo="DK" sex="T" s_adj="SA" unit="PC_ACT"><Obs TIME_PERIOD="2010-Q1" OBS_VALUE="7.8"/><Obs TIME_PERIOD="2010-Q2" OBS_VALUE="7.7"/><Obs TIME_PERIOD="2010-Q3" OBS_VALUE="7.6"/><Obs TIME_PERIOD="2010-Q4" OBS_VALUE="7.8"/><Obs TIME_PERIOD="2011-Q1" OBS_VALUE="8.0"/><Obs TIME_PERIOD="2011-Q2" OBS_VALUE="7.4"/><Obs TIME_PERIOD="2011-Q3" OBS_VALUE="7.6"/><Obs TIME_PERIOD="2011-Q4" OBS_VALUE="8.0"/><Obs TIME_PERIOD="2012-Q1" OBS_VALUE="7.9"/><Obs TIME_PERIOD="2012-Q2" OBS_VALUE="8.2"/><Obs TIME_PERIOD="2012-Q3" OBS_VALUE="7.8"/><Obs TIME_PERIOD="2012-Q4" OBS_VALUE="7.4"/><Obs TIME_PERIOD="2013-Q1" OBS_VALUE="7.6"/><Obs TIME_PERIOD="2013-Q2" OBS_VALUE="7.5"/><Obs TIME_PERIOD="2013-Q3" OBS_VALUE="7.4"/><Obs TIME_PERIOD="2013-Q4" OBS_VALUE="7.0"/><Obs TIME_PERIOD="2014-Q1" OBS_VALUE="7.1"/><Obs TIME_PERIOD="2014-Q2" OBS_VALUE="6.8"/><Obs TIME_PERIOD="2014-Q3" OBS_VALUE="7.0"/><Obs TIME_PERIOD="2014-Q4" OBS_VALUE="6.8"/><Obs TIME_PERIOD="2015-Q1" OBS_VALUE="6.4"/><Obs TIME_PERIOD="2015-Q2" OBS_VALUE="6.4"/><Obs TIME_PERIOD="2015-Q3" OBS_VALUE="6.2"/><Obs TIME_PERIOD="2015-Q4" OBS_VALUE="6.1"/><Obs TIME_PERIOD="2016-Q1" OBS_VALUE="6.1" OBS_FLAG="b"/><Obs TIME_PERIOD="2016-Q2" OBS_VALUE="6.0"/><Obs TIME_PERIOD="2016-Q3" OBS_VALUE="6.0"/><Obs TIME_PERIOD="2016-Q4" OBS_VALUE="5.9"/><Obs TIME_PERIOD="2017-Q1" OBS_VALUE="6.2" OBS_FLAG="b"/><Obs TIME_PERIOD="2017-Q2" OBS_VALUE="5.9"/><Obs TIME_PERIOD="2017-Q3" OBS_VALUE="5.9"/><Obs TIME_PERIOD="2017-Q4" OBS_VALUE="5.4"/><Obs TIME_PERIOD="2018-Q1" OBS_VALUE="5.2"/><Obs TIME_PERIOD="2018-Q2" OBS_VALUE="5.2"/><Obs TIME_PERIOD="2018-Q3" OBS_VALUE="4.8"/><Obs TIME_PERIOD="2018-Q4" OBS_VALUE="5.2"/><Obs TIME_PERIOD="2019-Q1" OBS_VALUE="5.2"/><Obs TIME_PERIOD="2019-Q2" OBS_VALUE="5.0"/><Obs TIME_PERIOD="2019-Q3" OBS_VALUE="4.9"/><Obs TIME_PERIOD="2019-Q4" OBS_VALUE="5.1"/><Obs TIME_PERIOD="2020-Q1" OBS_VALUE="4.9"/><Obs TIME_PERIOD="2020-Q2" OBS_VALUE="5.5"/><Obs TIME_PERIOD="2020-Q3" OBS_VALUE="6.3"/><Obs TIME_PERIOD="2020-Q4" OBS_VALUE="5.8"/><Obs TIME_PERIOD="2021-Q1" OBS_VALUE="6.1"/><Obs TIME_PERIOD="2021-Q2" OBS_VALUE="5.1"/><Obs TIME_PERIOD="2021-Q3" OBS_VALUE="4.8"/><Obs TIME_PERIOD="2021-Q4" OBS_VALUE="4.4"/><Obs TIME_PERIOD="2022-Q1" OBS_VALUE="4.3"/><Obs TIME_PERIOD="2022-Q2" OBS_VALUE="4.3"/><Obs TIME_PERIOD="2022-Q3" OBS_VALUE="4.6"/><Obs TIME_PERIOD="2022-Q4" OBS_VALUE="4.6"/><Obs TIME_PERIOD="2023-Q1" OBS_VALUE="4.7"/><Obs TIME_PERIOD="2023-Q2" OBS_VALUE="5.0"/><Obs TIME_PERIOD="2023-Q3" OBS_VALUE="4.9"/><Obs TIME_PERIOD="2023-Q4" OBS_VALUE="5.8" OBS_FLAG="b"/></Series><Series age="Y15-74" freq="Q" geo="EA20" sex="T" s_adj="SA" unit="PC_ACT"><Obs TIME_PERIOD="2010-Q1" OBS_VALUE="10.3"/><Obs TIME_PERIOD="2010-Q2" OBS_VALUE="10.3"/><Obs TIME_PERIOD="2010-Q3" OBS_VALUE="10.2"/><Obs TIME_PERIOD="2010-Q4" OBS_VALUE="10.2"/><Obs TIME_PERIOD="2011-Q1" OBS_VALUE="10.1"/><Obs TIME_PERIOD="2011-Q2" OBS_VALUE="10.1"/><Obs TIME_PERIOD="2011-Q3" OBS_VALUE="10.3"/><Obs TIME_PERIOD="2011-Q4" OBS_VALUE="10.7"/><Obs TIME_PERIOD="2012-Q1" OBS_VALUE="11.1"/><Obs TIME_PERIOD="2012-Q2" OBS_VALUE="11.4"/><Obs TIME_PERIOD="2012-Q3" OBS_VALUE="11.6"/><Obs TIME_PERIOD="2012-Q4" OBS_VALUE="12.0"/><Obs TIME_PERIOD="2013-Q1" OBS_VALUE="12.3"/><Obs TIME_PERIOD="2013-Q2" OBS_VALUE="12.2"/><Obs TIME_PERIOD="2013-Q3" OBS_VALUE="12.1"/><Obs TIME_PERIOD="2013-Q4" OBS_VALUE="12.0"/><Obs TIME_PERIOD="2014-Q1" OBS_VALUE="12.0"/><Obs TIME_PERIOD="2014-Q2" OBS_VALUE="11.7"/><Obs TIME_PERIOD="2014-Q3" OBS_VALUE="11.6"/><Obs TIME_PERIOD="2014-Q4" OBS_VALUE="11.6"/><Obs TIME_PERIOD="2015-Q1" OBS_VALUE="11.3"/><Obs TIME_PERIOD="2015-Q2" OBS_VALUE="11.1"/><Obs TIME_PERIOD="2015-Q3" OBS_VALUE="10.8"/><Obs TIME_PERIOD="2015-Q4" OBS_VALUE="10.7"/><Obs TIME_PERIOD="2016-Q1" OBS_VALUE="10.4"/><Obs TIME_PERIOD="2016-Q2" OBS_VALUE="10.2"/><Obs TIME_PERIOD="2016-Q3" OBS_VALUE="10.0"/><Obs TIME_PERIOD="2016-Q4" OBS_VALUE="9.8"/><Obs TIME_PERIOD="2017-Q1" OBS_VALUE="9.5"/><Obs TIME_PERIOD="2017-Q2" OBS_VALUE="9.2"/><Obs TIME_PERIOD="2017-Q3" OBS_VALUE="9.0"/><Obs TIME_PERIOD="2017-Q4" OBS_VALUE="8.8"/><Obs TIME_PERIOD="2018-Q1" OBS_VALUE="8.6"/><Obs TIME_PERIOD="2018-Q2" OBS_VALUE="8.4"/><Obs TIME_PERIOD="2018-Q3" OBS_VALUE="8.0"/><Obs TIME_PERIOD="2018-Q4" OBS_VALUE="8.0"/><Obs TIME_PERIOD="2019-Q1" OBS_VALUE="7.8"/><Obs TIME_PERIOD="2019-Q2" OBS_VALUE="7.6"/><Obs TIME_PERIOD="2019-Q3" OBS_VALUE="7.5"/><Obs TIME_PERIOD="2019-Q4" OBS_VALUE="7.4"/><Obs TIME_PERIOD="2020-Q1" OBS_VALUE="7.4"/><Obs TIME_PERIOD="2020-Q2" OBS_VALUE="7.6"/><Obs TIME_PERIOD="2020-Q3" OBS_VALUE="8.7"/><Obs TIME_PERIOD="2020-Q4" OBS_VALUE="8.2"/><Obs TIME_PERIOD="2021-Q1" OBS_VALUE="8.3"/><Obs TIME_PERIOD="2021-Q2" OBS_VALUE="8.1"/><Obs TIME_PERIOD="2021-Q3" OBS_VALUE="7.6"/><Obs TIME_PERIOD="2021-Q4" OBS_VALUE="7.2"/><Obs TIME_PERIOD="2022-Q1" OBS_VALUE="6.9"/><Obs TIME_PERIOD="2022-Q2" OBS_VALUE="6.8"/><Obs TIME_PERIOD="2022-Q3" OBS_VALUE="6.8"/><Obs TIME_PERIOD="2022-Q4" OBS_VALUE="6.7"/><Obs TIME_PERIOD="2023-Q1" OBS_VALUE="6.6"/><Obs TIME_PERIOD="2023-Q2" OBS_VALUE="6.5"/><Obs TIME_PERIOD="2023-Q3" OBS_VALUE="6.6"/><Obs TIME_PERIOD="2023-Q4" OBS_VALUE="6.5"/></Series><Series age="Y15-74" freq="Q" geo="EE" sex="T" s_adj="SA" unit="PC_ACT"><Obs TIME_PERIOD="2010-Q1" OBS_VALUE="19.2"/><Obs TIME_PERIOD="2010-Q2" OBS_VALUE="18.1"/><Obs TIME_PERIOD="2010-Q3" OBS_VALUE="15.4"/><Obs TIME_PERIOD="2010-Q4" OBS_VALUE="13.4"/><Obs TIME_PERIOD="2011-Q1" OBS_VALUE="14.1"/><Obs TIME_PERIOD="2011-Q2" OBS_VALUE="13.0"/><Obs TIME_PERIOD="2011-Q3" OBS_VALUE="10.8"/><Obs TIME_PERIOD="2011-Q4" OBS_VALUE="11.2"/><Obs TIME_PERIOD="2012-Q1" OBS_VALUE="11.2"/><Obs TIME_PERIOD="2012-Q2" OBS_VALUE="10.0"/><Obs TIME_PERIOD="2012-Q3" OBS_VALUE="9.5"/><Obs TIME_PERIOD="2012-Q4" OBS_VALUE="9.0"/><Obs TIME_PERIOD="2013-Q1" OBS_VALUE="9.8"/><Obs TIME_PERIOD="2013-Q2" OBS_VALUE="7.9"/><Obs TIME_PERIOD="2013-Q3" OBS_VALUE="7.9"/><Obs TIME_PERIOD="2013-Q4" OBS_VALUE="8.6"/><Obs TIME_PERIOD="2014-Q1" OBS_VALUE="8.4"/><Obs TIME_PERIOD="2014-Q2" OBS_VALUE="7.0"/><Obs TIME_PERIOD="2014-Q3" OBS_VALUE="7.5"/><Obs TIME_PERIOD="2014-Q4" OBS_VALUE="6.2"/><Obs TIME_PERIOD="2015-Q1" OBS_VALUE="6.7"/><Obs TIME_PERIOD="2015-Q2" OBS_VALUE="6.7"/><Obs TIME_PERIOD="2015-Q3" OBS_VALUE="5.5"/><Obs TIME_PERIOD="2015-Q4" OBS_VALUE="6.5"/><Obs TIME_PERIOD="2016-Q1" OBS_VALUE="6.6"/><Obs TIME_PERIOD="2016-Q2" OBS_VALUE="6.5"/><Obs TIME_PERIOD="2016-Q3" OBS_VALUE="7.6"/><Obs TIME_PERIOD="2016-Q4" OBS_VALUE="6.6"/><Obs TIME_PERIOD="2017-Q1" OBS_VALUE="5.7"/><Obs TIME_PERIOD="2017-Q2" OBS_VALUE="6.7"/><Obs TIME_PERIOD="2017-Q3" OBS_VALUE="5.2"/><Obs TIME_PERIOD="2017-Q4" OBS_VALUE="5.5"/><Obs TIME_PERIOD="2018-Q1" OBS_VALUE="6.7"/><Obs TIME_PERIOD="2018-Q2" OBS_VALUE="5.1"/><Obs TIME_PERIOD="2018-Q3" OBS_VALUE="5.3"/><Obs TIME_PERIOD="2018-Q4" OBS_VALUE="4.4"/><Obs TIME_PERIOD="2019-Q1" OBS_VALUE="4.7"/><Obs TIME_PERIOD="2019-Q2" OBS_VALUE="5.1"/><Obs TIME_PERIOD="2019-Q3" OBS_VALUE="4.0"/><Obs TIME_PERIOD="2019-Q4" OBS_VALUE="4.1"/><Obs TIME_PERIOD="2020-Q1" OBS_VALUE="5.1"/><Obs TIME_PERIOD="2020-Q2" OBS_VALUE="7.2"/><Obs TIME_PERIOD="2020-Q3" OBS_VALUE="7.7"/><Obs TIME_PERIOD="2020-Q4" OBS_VALUE="7.6"/><Obs TIME_PERIOD="2021-Q1" OBS_VALUE="7.0"/><Obs TIME_PERIOD="2021-Q2" OBS_VALUE="6.9"/><Obs TIME_PERIOD="2021-Q3" OBS_VALUE="5.8"/><Obs TIME_PERIOD="2021-Q4" OBS_VALUE="5.2"/><Obs TIME_PERIOD="2022-Q1" OBS_VALUE="5.5"/><Obs TIME_PERIOD="2022-Q2" OBS_VALUE="5.9"/><Obs TIME_PERIOD="2022-Q3" OBS_VALUE="5.7"/><Obs TIME_PERIOD="2022-Q4" OBS_VALUE="5.3"/><Obs TIME_PERIOD="2023-Q1" OBS_VALUE="5.3"/><Obs TIME_PERIOD="2023-Q2" OBS_VALUE="6.8"/><Obs TIME_PERIOD="2023-Q3" OBS_VALUE="7.4"/><Obs TIME_PERIOD="2023-Q4" OBS_VALUE="6.3"/></Series><Series age="Y15-74" freq="Q" geo="EL" sex="T" s_adj="SA" unit="PC_ACT"><Obs TIME_PERIOD="2010-Q1" OBS_VALUE="11.5"/><Obs TIME_PERIOD="2010-Q2" OBS_VALUE="12.5"/><Obs TIME_PERIOD="2010-Q3" OBS_VALUE="13.3"/><Obs TIME_PERIOD="2010-Q4" OBS_VALUE="14.5"/><Obs TIME_PERIOD="2011-Q1" OBS_VALUE="15.7"/><Obs TIME_PERIOD="2011-Q2" OBS_VALUE="17.0"/><Obs TIME_PERIOD="2011-Q3" OBS_VALUE="18.8"/><Obs TIME_PERIOD="2011-Q4" OBS_VALUE="20.8"/><Obs TIME_PERIOD="2012-Q1" OBS_VALUE="22.4"/><Obs TIME_PERIOD="2012-Q2" OBS_VALUE="24.3"/><Obs TIME_PERIOD="2012-Q3" OBS_VALUE="25.9"/><Obs TIME_PERIOD="2012-Q4" OBS_VALUE="26.6"/><Obs TIME_PERIOD="2013-Q1" OBS_VALUE="27.5"/><Obs TIME_PERIOD="2013-Q2" OBS_VALUE="27.9"/><Obs TIME_PERIOD="2013-Q3" OBS_VALUE="28.0"/><Obs TIME_PERIOD="2013-Q4" OBS_VALUE="27.8"/><Obs TIME_PERIOD="2014-Q1" OBS_VALUE="27.3"/><Obs TIME_PERIOD="2014-Q2" OBS_VALUE="27.0"/><Obs TIME_PERIOD="2014-Q3" OBS_VALUE="26.4"/><Obs TIME_PERIOD="2014-Q4" OBS_VALUE="26.0"/><Obs TIME_PERIOD="2015-Q1" OBS_VALUE="25.7"/><Obs TIME_PERIOD="2015-Q2" OBS_VALUE="25.0"/><Obs TIME_PERIOD="2015-Q3" OBS_VALUE="24.8"/><Obs TIME_PERIOD="2015-Q4" OBS_VALUE="24.3"/><Obs TIME_PERIOD="2016-Q1" OBS_VALUE="24.2"/><Obs TIME_PERIOD="2016-Q2" OBS_VALUE="23.9"/><Obs TIME_PERIOD="2016-Q3" OBS_VALUE="23.8"/><Obs TIME_PERIOD="2016-Q4" OBS_VALUE="23.5"/><Obs TIME_PERIOD="2017-Q1" OBS_VALUE="22.8"/><Obs TIME_PERIOD="2017-Q2" OBS_VALUE="22.1"/><Obs TIME_PERIOD="2017-Q3" OBS_VALUE="21.3"/><Obs TIME_PERIOD="2017-Q4" OBS_VALUE="21.1"/><Obs TIME_PERIOD="2018-Q1" OBS_VALUE="20.6"/><Obs TIME_PERIOD="2018-Q2" OBS_VALUE="19.9"/><Obs TIME_PERIOD="2018-Q3" OBS_VALUE="19.4"/><Obs TIME_PERIOD="2018-Q4" OBS_VALUE="19.1"/><Obs TIME_PERIOD="2019-Q1" OBS_VALUE="18.9"/><Obs TIME_PERIOD="2019-Q2" OBS_VALUE="17.8"/><Obs TIME_PERIOD="2019-Q3" OBS_VALUE="17.6"/><Obs TIME_PERIOD="2019-Q4" OBS_VALUE="17.1"/><Obs TIME_PERIOD="2020-Q1" OBS_VALUE="16.7"/><Obs TIME_PERIOD="2020-Q2" OBS_VALUE="19.3"/><Obs TIME_PERIOD="2020-Q3" OBS_VALUE="17.3"/><Obs TIME_PERIOD="2020-Q4" OBS_VALUE="17.1"/><Obs TIME_PERIOD="2021-Q1" OBS_VALUE="16.6"/><Obs TIME_PERIOD="2021-Q2" OBS_VALUE="15.6"/><Obs TIME_PERIOD="2021-Q3" OBS_VALUE="13.9"/><Obs TIME_PERIOD="2021-Q4" OBS_VALUE="13.2"/><Obs TIME_PERIOD="2022-Q1" OBS_VALUE="13.1"/><Obs TIME_PERIOD="2022-Q2" OBS_VALUE="12.5"/><Obs TIME_PERIOD="2022-Q3" OBS_VALUE="12.2"/><Obs TIME_PERIOD="2022-Q4" OBS_VALUE="11.9"/><Obs TIME_PERIOD="2023-Q1" OBS_VALUE="11.4"/><Obs TIME_PERIOD="2023-Q2" OBS_VALUE="11.2"/><Obs TIME_PERIOD="2023-Q3" OBS_VALUE="11.1"/><Obs TIME_PERIOD="2023-Q4" OBS_VALUE="10.6"/></Series><Series age="Y15-74" freq="Q" geo="ES" sex="T" s_adj="SA" unit="PC_ACT"><Obs TIME_PERIOD="2010-Q1" OBS_VALUE="19.3"/><Obs TIME_PERIOD="2010-Q2" OBS_VALUE="19.9"/><Obs TIME_PERIOD="2010-Q3" OBS_VALUE="20.0"/><Obs TIME_PERIOD="2010-Q4" OBS_VALUE="20.2"/><Obs TIME_PERIOD="2011-Q1" OBS_VALUE="20.5"/><Obs TIME_PERIOD="2011-Q2" OBS_VALUE="20.8"/><Obs TIME_PERIOD="2011-Q3" OBS_VALUE="21.7"/><Obs TIME_PERIOD="2011-Q4" OBS_VALUE="22.6"/><Obs TIME_PERIOD="2012-Q1" OBS_VALUE="23.6"/><Obs TIME_PERIOD="2012-Q2" OBS_VALUE="24.5"/><Obs TIME_PERIOD="2012-Q3" OBS_VALUE="25.2"/><Obs TIME_PERIOD="2012-Q4" OBS_VALUE="25.8"/><Obs TIME_PERIOD="2013-Q1" OBS_VALUE="26.3"/><Obs TIME_PERIOD="2013-Q2" OBS_VALUE="26.2"/><Obs TIME_PERIOD="2013-Q3" OBS_VALUE="26.1"/><Obs TIME_PERIOD="2013-Q4" OBS_VALUE="25.8"/><Obs TIME_PERIOD="2014-Q1" OBS_VALUE="25.3"/><Obs TIME_PERIOD="2014-Q2" OBS_VALUE="24.6"/><Obs TIME_PERIOD="2014-Q3" OBS_VALUE="24.2"/><Obs TIME_PERIOD="2014-Q4" OBS_VALUE="23.8"/><Obs TIME_PERIOD="2015-Q1" OBS_VALUE="23.1"/><Obs TIME_PERIOD="2015-Q2" OBS_VALUE="22.5"/><Obs TIME_PERIOD="2015-Q3" OBS_VALUE="21.7"/><Obs TIME_PERIOD="2015-Q4" OBS_VALUE="21.0"/><Obs TIME_PERIOD="2016-Q1" OBS_VALUE="20.4"/><Obs TIME_PERIOD="2016-Q2" OBS_VALUE="20.1"/><Obs TIME_PERIOD="2016-Q3" OBS_VALUE="19.4"/><Obs TIME_PERIOD="2016-Q4" OBS_VALUE="18.7"/><Obs TIME_PERIOD="2017-Q1" OBS_VALUE="18.1"/><Obs TIME_PERIOD="2017-Q2" OBS_VALUE="17.3"/><Obs TIME_PERIOD="2017-Q3" OBS_VALUE="16.8"/><Obs TIME_PERIOD="2017-Q4" OBS_VALUE="16.6"/><Obs TIME_PERIOD="2018-Q1" OBS_VALUE="16.2"/><Obs TIME_PERIOD="2018-Q2" OBS_VALUE="15.4"/><Obs TIME_PERIOD="2018-Q3" OBS_VALUE="14.9"/><Obs TIME_PERIOD="2018-Q4" OBS_VALUE="14.6"/><Obs TIME_PERIOD="2019-Q1" OBS_VALUE="14.2"/><Obs TIME_PERIOD="2019-Q2" OBS_VALUE="14.2"/><Obs TIME_PERIOD="2019-Q3" OBS_VALUE="14.1"/><Obs TIME_PERIOD="2019-Q4" OBS_VALUE="13.9"/><Obs TIME_PERIOD="2020-Q1" OBS_VALUE="14.0"/><Obs TIME_PERIOD="2020-Q2" OBS_VALUE="15.5"/><Obs TIME_PERIOD="2020-Q3" OBS_VALUE="16.4"/><Obs TIME_PERIOD="2020-Q4" OBS_VALUE="16.2"/><Obs TIME_PERIOD="2021-Q1" OBS_VALUE="15.7" OBS_FLAG="b"/><Obs TIME_PERIOD="2021-Q2" OBS_VALUE="15.6"/><Obs TIME_PERIOD="2021-Q3" OBS_VALUE="14.8"/><Obs TIME_PERIOD="2021-Q4" OBS_VALUE="13.6"/><Obs TIME_PERIOD="2022-Q1" OBS_VALUE="13.3" OBS_FLAG="d"/><Obs TIME_PERIOD="2022-Q2" OBS_VALUE="13.0" OBS_FLAG="d"/><Obs TIME_PERIOD="2022-Q3" OBS_VALUE="12.8" OBS_FLAG="d"/><Obs TIME_PERIOD="2022-Q4" OBS_VALUE="13.0" OBS_FLAG="d"/><Obs TIME_PERIOD="2023-Q1" OBS_VALUE="12.8" OBS_FLAG="d"/><Obs TIME_PERIOD="2023-Q2" OBS_VALUE="12.1" OBS_FLAG="d"/><Obs TIME_PERIOD="2023-Q3" OBS_VALUE="12.0" OBS_FLAG="d"/><Obs TIME_PERIOD="2023-Q4" OBS_VALUE="11.8" OBS_FLAG="d"/></Series><Series age="Y15-74" freq="Q" geo="EU27_2020" sex="T" s_adj="SA" unit="PC_ACT"><Obs TIME_PERIOD="2010-Q1" OBS_VALUE="10.2"/><Obs TIME_PERIOD="2010-Q2" OBS_VALUE="10.1"/><Obs TIME_PERIOD="2010-Q3" OBS_VALUE="10.0"/><Obs TIME_PERIOD="2010-Q4" OBS_VALUE="10.0"/><Obs TIME_PERIOD="2011-Q1" OBS_VALUE="10.0"/><Obs TIME_PERIOD="2011-Q2" OBS_VALUE="9.9"/><Obs TIME_PERIOD="2011-Q3" OBS_VALUE="10.1"/><Obs TIME_PERIOD="2011-Q4" OBS_VALUE="10.4"/><Obs TIME_PERIOD="2012-Q1" OBS_VALUE="10.7"/><Obs TIME_PERIOD="2012-Q2" OBS_VALUE="11.0"/><Obs TIME_PERIOD="2012-Q3" OBS_VALUE="11.2"/><Obs TIME_PERIOD="2012-Q4" OBS_VALUE="11.4"/><Obs TIME_PERIOD="2013-Q1" OBS_VALUE="11.7"/><Obs TIME_PERIOD="2013-Q2" OBS_VALUE="11.6"/><Obs TIME_PERIOD="2013-Q3" OBS_VALUE="11.5"/><Obs TIME_PERIOD="2013-Q4" OBS_VALUE="11.4"/><Obs TIME_PERIOD="2014-Q1" OBS_VALUE="11.4"/><Obs TIME_PERIOD="2014-Q2" OBS_VALUE="11.0"/><Obs TIME_PERIOD="2014-Q3" OBS_VALUE="10.9"/><Obs TIME_PERIOD="2014-Q4" OBS_VALUE="10.8"/><Obs TIME_PERIOD="2015-Q1" OBS_VALUE="10.6"/><Obs TIME_PERIOD="2015-Q2" OBS_VALUE="10.3"/><Obs TIME_PERIOD="2015-Q3" OBS_VALUE="10.0"/><Obs TIME_PERIOD="2015-Q4" OBS_VALUE="9.9"/><Obs TIME_PERIOD="2016-Q1" OBS_VALUE="9.6"/><Obs TIME_PERIOD="2016-Q2" OBS_VALUE="9.4"/><Obs TIME_PERIOD="2016-Q3" OBS_VALUE="9.1"/><Obs TIME_PERIOD="2016-Q4" OBS_VALUE="8.9"/><Obs TIME_PERIOD="2017-Q1" OBS_VALUE="8.7"/><Obs TIME_PERIOD="2017-Q2" OBS_VALUE="8.4"/><Obs TIME_PERIOD="2017-Q3" OBS_VALUE="8.2"/><Obs TIME_PERIOD="2017-Q4" OBS_VALUE="7.9"/><Obs TIME_PERIOD="2018-Q1" OBS_VALUE="7.7"/><Obs TIME_PERIOD="2018-Q2" OBS_VALUE="7.5"/><Obs TIME_PERIOD="2018-Q3" OBS_VALUE="7.2"/><Obs TIME_PERIOD="2018-Q4" OBS_VALUE="7.1"/><Obs TIME_PERIOD="2019-Q1" OBS_VALUE="7.0"/><Obs TIME_PERIOD="2019-Q2" OBS_VALUE="6.8"/><Obs TIME_PERIOD="2019-Q3" OBS_VALUE="6.7"/><Obs TIME_PERIOD="2019-Q4" OBS_VALUE="6.7"/><Obs TIME_PERIOD="2020-Q1" OBS_VALUE="6.6"/><Obs TIME_PERIOD="2020-Q2" OBS_VALUE="7.0"/><Obs TIME_PERIOD="2020-Q3" OBS_VALUE="7.9"/><Obs TIME_PERIOD="2020-Q4" OBS_VALUE="7.5"/><Obs TIME_PERIOD="2021-Q1" OBS_VALUE="7.6"/><Obs TIME_PERIOD="2021-Q2" OBS_VALUE="7.3"/><Obs TIME_PERIOD="2021-Q3" OBS_VALUE="6.9"/><Obs TIME_PERIOD="2021-Q4" OBS_VALUE="6.5"/><Obs TIME_PERIOD="2022-Q1" OBS_VALUE="6.3"/><Obs TIME_PERIOD="2022-Q2" OBS_VALUE="6.2"/><Obs TIME_PERIOD="2022-Q3" OBS_VALUE="6.2"/><Obs TIME_PERIOD="2022-Q4" OBS_VALUE="6.1"/><Obs TIME_PERIOD="2023-Q1" OBS_VALUE="6.1"/><Obs TIME_PERIOD="2023-Q2" OBS_VALUE="6.0"/><Obs TIME_PERIOD="2023-Q3" OBS_VALUE="6.1"/><Obs TIME_PERIOD="2023-Q4" OBS_VALUE="6.1"/></Series><Series age="Y15-74" freq="Q" geo="FI" sex="T" s_adj="SA" unit="PC_ACT"><Obs TIME_PERIOD="2010-Q1" OBS_VALUE="9.0"/><Obs TIME_PERIOD="2010-Q2" OBS_VALUE="8.5"/><Obs TIME_PERIOD="2010-Q3" OBS_VALUE="8.4"/><Obs TIME_PERIOD="2010-Q4" OBS_VALUE="8.4"/><Obs TIME_PERIOD="2011-Q1" OBS_VALUE="8.5"/><Obs TIME_PERIOD="2011-Q2" OBS_VALUE="7.9"/><Obs TIME_PERIOD="2011-Q3" OBS_VALUE="7.9"/><Obs TIME_PERIOD="2011-Q4" OBS_VALUE="7.7"/><Obs TIME_PERIOD="2012-Q1" OBS_VALUE="7.7"/><Obs TIME_PERIOD="2012-Q2" OBS_VALUE="7.8"/><Obs TIME_PERIOD="2012-Q3" OBS_VALUE="8.1"/><Obs TIME_PERIOD="2012-Q4" OBS_VALUE="7.9"/><Obs TIME_PERIOD="2013-Q1" OBS_VALUE="8.4"/><Obs TIME_PERIOD="2013-Q2" OBS_VALUE="8.2"/><Obs TIME_PERIOD="2013-Q3" OBS_VALUE="8.2"/><Obs TIME_PERIOD="2013-Q4" OBS_VALUE="8.5"/><Obs TIME_PERIOD="2014-Q1" OBS_VALUE="8.6"/><Obs TIME_PERIOD="2014-Q2" OBS_VALUE="8.7"/><Obs TIME_PERIOD="2014-Q3" OBS_VALUE="8.5"/><Obs TIME_PERIOD="2014-Q4" OBS_VALUE="9.2"/><Obs TIME_PERIOD="2015-Q1" OBS_VALUE="9.3"/><Obs TIME_PERIOD="2015-Q2" OBS_VALUE="9.5"/><Obs TIME_PERIOD="2015-Q3" OBS_VALUE="9.4"/><Obs TIME_PERIOD="2015-Q4" OBS_VALUE="9.5"/><Obs TIME_PERIOD="2016-Q1" OBS_VALUE="9.3"/><Obs TIME_PERIOD="2016-Q2" OBS_VALUE="8.9"/><Obs TIME_PERIOD="2016-Q3" OBS_VALUE="8.6"/><Obs TIME_PERIOD="2016-Q4" OBS_VALUE="8.9"/><Obs TIME_PERIOD="2017-Q1" OBS_VALUE="9.0"/><Obs TIME_PERIOD="2017-Q2" OBS_VALUE="8.9"/><Obs TIME_PERIOD="2017-Q3" OBS_VALUE="8.6"/><Obs TIME_PERIOD="2017-Q4" OBS_VALUE="8.3"/><Obs TIME_PERIOD="2018-Q1" OBS_VALUE="8.4"/><Obs TIME_PERIOD="2018-Q2" OBS_VALUE="7.4"/><Obs TIME_PERIOD="2018-Q3" OBS_VALUE="7.2"/><Obs TIME_PERIOD="2018-Q4" OBS_VALUE="6.8"/><Obs TIME_PERIOD="2019-Q1" OBS_VALUE="6.7"/><Obs TIME_PERIOD="2019-Q2" OBS_VALUE="6.9"/><Obs TIME_PERIOD="2019-Q3" OBS_VALUE="6.7"/><Obs TIME_PERIOD="2019-Q4" OBS_VALUE="6.8"/><Obs TIME_PERIOD="2020-Q1" OBS_VALUE="6.8"/><Obs TIME_PERIOD="2020-Q2" OBS_VALUE="7.8"/><Obs TIME_PERIOD="2020-Q3" OBS_VALUE="8.3"/><Obs TIME_PERIOD="2020-Q4" OBS_VALUE="8.1"/><Obs TIME_PERIOD="2021-Q1" OBS_VALUE="8.1"/><Obs TIME_PERIOD="2021-Q2" OBS_VALUE="8.1"/><Obs TIME_PERIOD="2021-Q3" OBS_VALUE="7.3"/><Obs TIME_PERIOD="2021-Q4" OBS_VALUE="6.9"/><Obs TIME_PERIOD="2022-Q1" OBS_VALUE="6.7"/><Obs TIME_PERIOD="2022-Q2" OBS_VALUE="6.4"/><Obs TIME_PERIOD="2022-Q3" OBS_VALUE="7.1"/><Obs TIME_PERIOD="2022-Q4" OBS_VALUE="6.8"/><Obs TIME_PERIOD="2023-Q1" OBS_VALUE="6.8"/><Obs TIME_PERIOD="2023-Q2" OBS_VALUE="7.2"/><Obs TIME_PERIOD="2023-Q3" OBS_VALUE="7.3"/><Obs TIME_PERIOD="2023-Q4" OBS_VALUE="7.5"/></Series><Series age="Y15-74" freq="Q" geo="FR" sex="T" s_adj="SA" unit="PC_ACT"><Obs TIME_PERIOD="2010-Q1" OBS_VALUE="9.4"/><Obs TIME_PERIOD="2010-Q2" OBS_VALUE="9.3"/><Obs TIME_PERIOD="2010-Q3" OBS_VALUE="9.2"/><Obs TIME_PERIOD="2010-Q4" OBS_VALUE="9.2"/><Obs TIME_PERIOD="2011-Q1" OBS_VALUE="9.2"/><Obs TIME_PERIOD="2011-Q2" OBS_VALUE="9.1"/><Obs TIME_PERIOD="2011-Q3" OBS_VALUE="9.2"/><Obs TIME_PERIOD="2011-Q4" OBS_VALUE="9.4"/><Obs TIME_PERIOD="2012-Q1" OBS_VALUE="9.5"/><Obs TIME_PERIOD="2012-Q2" OBS_VALUE="9.7"/><Obs TIME_PERIOD="2012-Q3" OBS_VALUE="9.7"/><Obs TIME_PERIOD="2012-Q4" OBS_VALUE="10.2"/><Obs TIME_PERIOD="2013-Q1" OBS_VALUE="10.4"/><Obs TIME_PERIOD="2013-Q2" OBS_VALUE="10.4"/><Obs TIME_PERIOD="2013-Q3" OBS_VALUE="10.2"/><Obs TIME_PERIOD="2013-Q4" OBS_VALUE="10.1"/><Obs TIME_PERIOD="2014-Q1" OBS_VALUE="10.2"/><Obs TIME_PERIOD="2014-Q2" OBS_VALUE="10.1"/><Obs TIME_PERIOD="2014-Q3" OBS_VALUE="10.2"/><Obs TIME_PERIOD="2014-Q4" OBS_VALUE="10.5"/><Obs TIME_PERIOD="2015-Q1" OBS_VALUE="10.4"/><Obs TIME_PERIOD="2015-Q2" OBS_VALUE="10.5"/><Obs TIME_PERIOD="2015-Q3" OBS_VALUE="10.3"/><Obs TIME_PERIOD="2015-Q4" OBS_VALUE="10.3"/><Obs TIME_PERIOD="2016-Q1" OBS_VALUE="10.3"/><Obs TIME_PERIOD="2016-Q2" OBS_VALUE="10.0"/><Obs TIME_PERIOD="2016-Q3" OBS_VALUE="9.9"/><Obs TIME_PERIOD="2016-Q4" OBS_VALUE="10.1"/><Obs TIME_PERIOD="2017-Q1" OBS_VALUE="9.6"/><Obs TIME_PERIOD="2017-Q2" OBS_VALUE="9.5"/><Obs TIME_PERIOD="2017-Q3" OBS_VALUE="9.5"/><Obs TIME_PERIOD="2017-Q4" OBS_VALUE="9.1"/><Obs TIME_PERIOD="2018-Q1" OBS_VALUE="9.3"/><Obs TIME_PERIOD="2018-Q2" OBS_VALUE="9.1"/><Obs TIME_PERIOD="2018-Q3" OBS_VALUE="8.9"/><Obs TIME_PERIOD="2018-Q4" OBS_VALUE="8.8"/><Obs TIME_PERIOD="2019-Q1" OBS_VALUE="8.7"/><Obs TIME_PERIOD="2019-Q2" OBS_VALUE="8.4"/><Obs TIME_PERIOD="2019-Q3" OBS_VALUE="8.3"/><Obs TIME_PERIOD="2019-Q4" OBS_VALUE="8.3"/><Obs TIME_PERIOD="2020-Q1" OBS_VALUE="7.9"/><Obs TIME_PERIOD="2020-Q2" OBS_VALUE="7.2"/><Obs TIME_PERIOD="2020-Q3" OBS_VALUE="8.9"/><Obs TIME_PERIOD="2020-Q4" OBS_VALUE="8.1"/><Obs TIME_PERIOD="2021-Q1" OBS_VALUE="8.2" OBS_FLAG="d"/><Obs TIME_PERIOD="2021-Q2" OBS_VALUE="8.0" OBS_FLAG="d"/><Obs TIME_PERIOD="2021-Q3" OBS_VALUE="7.9" OBS_FLAG="d"/><Obs TIME_PERIOD="2021-Q4" OBS_VALUE="7.5" OBS_FLAG="d"/><Obs TIME_PERIOD="2022-Q1" OBS_VALUE="7.4" OBS_FLAG="d"/><Obs TIME_PERIOD="2022-Q2" OBS_VALUE="7.5" OBS_FLAG="d"/><Obs TIME_PERIOD="2022-Q3" OBS_VALUE="7.3" OBS_FLAG="d"/><Obs TIME_PERIOD="2022-Q4" OBS_VALUE="7.2" OBS_FLAG="d"/><Obs TIME_PERIOD="2023-Q1" OBS_VALUE="7.1" OBS_FLAG="d"/><Obs TIME_PERIOD="2023-Q2" OBS_VALUE="7.3" OBS_FLAG="d"/><Obs TIME_PERIOD="2023-Q3" OBS_VALUE="7.4" OBS_FLAG="d"/><Obs TIME_PERIOD="2023-Q4" OBS_VALUE="7.6" OBS_FLAG="d"/></Series><Series age="Y15-74" freq="Q" geo="HR" sex="T" s_adj="SA" unit="PC_ACT"><Obs TIME_PERIOD="2010-Q1" OBS_VALUE="10.3"/><Obs TIME_PERIOD="2010-Q2" OBS_VALUE="11.9"/><Obs TIME_PERIOD="2010-Q3" OBS_VALUE="12.2"/><Obs TIME_PERIOD="2010-Q4" OBS_VALUE="12.3"/><Obs TIME_PERIOD="2011-Q1" OBS_VALUE="13.2"/><Obs TIME_PERIOD="2011-Q2" OBS_VALUE="14.1"/><Obs TIME_PERIOD="2011-Q3" OBS_VALUE="13.9"/><Obs TIME_PERIOD="2011-Q4" OBS_VALUE="13.7"/><Obs TIME_PERIOD="2012-Q1" OBS_VALUE="15.2"/><Obs TIME_PERIOD="2012-Q2" OBS_VALUE="15.2"/><Obs TIME_PERIOD="2012-Q3" OBS_VALUE="15.9"/><Obs TIME_PERIOD="2012-Q4" OBS_VALUE="17.6"/><Obs TIME_PERIOD="2013-Q1" OBS_VALUE="17.0"/><Obs TIME_PERIOD="2013-Q2" OBS_VALUE="17.1"/><Obs TIME_PERIOD="2013-Q3" OBS_VALUE="17.6"/><Obs TIME_PERIOD="2013-Q4" OBS_VALUE="17.2"/><Obs TIME_PERIOD="2014-Q1" OBS_VALUE="18.0"/><Obs TIME_PERIOD="2014-Q2" OBS_VALUE="17.3"/><Obs TIME_PERIOD="2014-Q3" OBS_VALUE="16.8"/><Obs TIME_PERIOD="2014-Q4" OBS_VALUE="17.6"/><Obs TIME_PERIOD="2015-Q1" OBS_VALUE="16.6"/><Obs TIME_PERIOD="2015-Q2" OBS_VALUE="16.0"/><Obs TIME_PERIOD="2015-Q3" OBS_VALUE="16.7"/><Obs TIME_PERIOD="2015-Q4" OBS_VALUE="15.5"/><Obs TIME_PERIOD="2016-Q1" OBS_VALUE="14.0"/><Obs TIME_PERIOD="2016-Q2" OBS_VALUE="13.3"/><Obs TIME_PERIOD="2016-Q3" OBS_VALUE="12.5"/><Obs TIME_PERIOD="2016-Q4" OBS_VALUE="12.9"/><Obs TIME_PERIOD="2017-Q1" OBS_VALUE="12.7"/><Obs TIME_PERIOD="2017-Q2" OBS_VALUE="11.5"/><Obs TIME_PERIOD="2017-Q3" OBS_VALUE="10.2"/><Obs TIME_PERIOD="2017-Q4" OBS_VALUE="10.1"/><Obs TIME_PERIOD="2018-Q1" OBS_VALUE="9.4"/><Obs TIME_PERIOD="2018-Q2" OBS_VALUE="8.3"/><Obs TIME_PERIOD="2018-Q3" OBS_VALUE="8.2"/><Obs TIME_PERIOD="2018-Q4" OBS_VALUE="7.8"/><Obs TIME_PERIOD="2019-Q1" OBS_VALUE="7.0"/><Obs TIME_PERIOD="2019-Q2" OBS_VALUE="6.8"/><Obs TIME_PERIOD="2019-Q3" OBS_VALUE="6.3"/><Obs TIME_PERIOD="2019-Q4" OBS_VALUE="6.5"/><Obs TIME_PERIOD="2020-Q1" OBS_VALUE="6.5"/><Obs TIME_PERIOD="2020-Q2" OBS_VALUE="7.2"/><Obs TIME_PERIOD="2020-Q3" OBS_VALUE="8.1"/><Obs TIME_PERIOD="2020-Q4" OBS_VALUE="8.4"/><Obs TIME_PERIOD="2021-Q1" OBS_VALUE="8.9"/><Obs TIME_PERIOD="2021-Q2" OBS_VALUE="8.3"/><Obs TIME_PERIOD="2021-Q3" OBS_VALUE="7.1"/><Obs TIME_PERIOD="2021-Q4" OBS_VALUE="6.4"/><Obs TIME_PERIOD="2022-Q1" OBS_VALUE="6.4"/><Obs TIME_PERIOD="2022-Q2" OBS_VALUE="7.4"/><Obs TIME_PERIOD="2022-Q3" OBS_VALUE="7.4"/><Obs TIME_PERIOD="2022-Q4" OBS_VALUE="6.5"/><Obs TIME_PERIOD="2023-Q1" OBS_VALUE="6.4" OBS_FLAG="b"/><Obs TIME_PERIOD="2023-Q2" OBS_VALUE="6.0"/><Obs TIME_PERIOD="2023-Q3" OBS_VALUE="6.2"/><Obs TIME_PERIOD="2023-Q4" OBS_VALUE="5.6"/></Series><Series age="Y15-74" freq="Q" geo="HU" sex="T" s_adj="SA" unit="PC_ACT"><Obs TIME_PERIOD="2010-Q1" OBS_VALUE="10.9"/><Obs TIME_PERIOD="2010-Q2" OBS_VALUE="10.9"/><Obs TIME_PERIOD="2010-Q3" OBS_VALUE="10.7"/><Obs TIME_PERIOD="2010-Q4" OBS_VALUE="10.7"/><Obs TIME_PERIOD="2011-Q1" OBS_VALUE="10.9"/><Obs TIME_PERIOD="2011-Q2" OBS_VALUE="10.6"/><Obs TIME_PERIOD="2011-Q3" OBS_VALUE="10.6"/><Obs TIME_PERIOD="2011-Q4" OBS_VALUE="10.6"/><Obs TIME_PERIOD="2012-Q1" OBS_VALUE="11.1"/><Obs TIME_PERIOD="2012-Q2" OBS_VALUE="10.7"/><Obs TIME_PERIOD="2012-Q3" OBS_VALUE="10.4"/><Obs TIME_PERIOD="2012-Q4" OBS_VALUE="10.5"/><Obs TIME_PERIOD="2013-Q1" OBS_VALUE="10.8"/><Obs TIME_PERIOD="2013-Q2" OBS_VALUE="9.9"/><Obs TIME_PERIOD="2013-Q3" OBS_VALUE="9.7"/><Obs TIME_PERIOD="2013-Q4" OBS_VALUE="9.0"/><Obs TIME_PERIOD="2014-Q1" OBS_VALUE="7.7"/><Obs TIME_PERIOD="2014-Q2" OBS_VALUE="7.9"/><Obs TIME_PERIOD="2014-Q3" OBS_VALUE="7.3"/><Obs TIME_PERIOD="2014-Q4" OBS_VALUE="7.1"/><Obs TIME_PERIOD="2015-Q1" OBS_VALUE="7.3"/><Obs TIME_PERIOD="2015-Q2" OBS_VALUE="6.8"/><Obs TIME_PERIOD="2015-Q3" OBS_VALUE="6.4"/><Obs TIME_PERIOD="2015-Q4" OBS_VALUE="6.1"/><Obs TIME_PERIOD="2016-Q1" OBS_VALUE="5.6"/><Obs TIME_PERIOD="2016-Q2" OBS_VALUE="5.0"/><Obs TIME_PERIOD="2016-Q3" OBS_VALUE="4.8"/><Obs TIME_PERIOD="2016-Q4" OBS_VALUE="4.4"/><Obs TIME_PERIOD="2017-Q1" OBS_VALUE="4.2"/><Obs TIME_PERIOD="2017-Q2" OBS_VALUE="4.2"/><Obs TIME_PERIOD="2017-Q3" OBS_VALUE="4.0"/><Obs TIME_PERIOD="2017-Q4" OBS_VALUE="3.8"/><Obs TIME_PERIOD="2018-Q1" OBS_VALUE="3.6"/><Obs TIME_PERIOD="2018-Q2" OBS_VALUE="3.5"/><Obs TIME_PERIOD="2018-Q3" OBS_VALUE="3.7"/><Obs TIME_PERIOD="2018-Q4" OBS_VALUE="3.5"/><Obs TIME_PERIOD="2019-Q1" OBS_VALUE="3.3"/><Obs TIME_PERIOD="2019-Q2" OBS_VALUE="3.3"/><Obs TIME_PERIOD="2019-Q3" OBS_VALUE="3.4"/><Obs TIME_PERIOD="2019-Q4" OBS_VALUE="3.3"/><Obs TIME_PERIOD="2020-Q1" OBS_VALUE="3.5"/><Obs TIME_PERIOD="2020-Q2" OBS_VALUE="4.5"/><Obs TIME_PERIOD="2020-Q3" OBS_VALUE="4.3"/><Obs TIME_PERIOD="2020-Q4" OBS_VALUE="4.1"/><Obs TIME_PERIOD="2021-Q1" OBS_VALUE="4.3"/><Obs TIME_PERIOD="2021-Q2" OBS_VALUE="4.2"/><Obs TIME_PERIOD="2021-Q3" OBS_VALUE="3.9"/><Obs TIME_PERIOD="2021-Q4" OBS_VALUE="3.8"/><Obs TIME_PERIOD="2022-Q1" OBS_VALUE="3.6"/><Obs TIME_PERIOD="2022-Q2" OBS_VALUE="3.3"/><Obs TIME_PERIOD="2022-Q3" OBS_VALUE="3.7"/><Obs TIME_PERIOD="2022-Q4" OBS_VALUE="3.9"/><Obs TIME_PERIOD="2023-Q1" OBS_VALUE="3.9"/><Obs TIME_PERIOD="2023-Q2" OBS_VALUE="4.0"/><Obs TIME_PERIOD="2023-Q3" OBS_VALUE="4.1"/><Obs TIME_PERIOD="2023-Q4" OBS_VALUE="4.5"/></Series><Series age="Y15-74" freq="Q" geo="IE" sex="T" s_adj="SA" unit="PC_ACT"><Obs TIME_PERIOD="2010-Q1" OBS_VALUE="14.1"/><Obs TIME_PERIOD="2010-Q2" OBS_VALUE="14.3"/><Obs TIME_PERIOD="2010-Q3" OBS_VALUE="14.6"/><Obs TIME_PERIOD="2010-Q4" OBS_VALUE="15.4"/><Obs TIME_PERIOD="2011-Q1" OBS_VALUE="15.3"/><Obs TIME_PERIOD="2011-Q2" OBS_VALUE="15.1"/><Obs TIME_PERIOD="2011-Q3" OBS_VALUE="15.6"/><Obs TIME_PERIOD="2011-Q4" OBS_VALUE="15.7"/><Obs TIME_PERIOD="2012-Q1" OBS_VALUE="15.9"/><Obs TIME_PERIOD="2012-Q2" OBS_VALUE="15.7"/><Obs TIME_PERIOD="2012-Q3" OBS_VALUE="15.6"/><Obs TIME_PERIOD="2012-Q4" OBS_VALUE="15.0"/><Obs TIME_PERIOD="2013-Q1" OBS_VALUE="14.5"/><Obs TIME_PERIOD="2013-Q2" OBS_VALUE="14.3"/><Obs TIME_PERIOD="2013-Q3" OBS_VALUE="13.5"/><Obs TIME_PERIOD="2013-Q4" OBS_VALUE="12.8"/><Obs TIME_PERIOD="2014-Q1" OBS_VALUE="12.8"/><Obs TIME_PERIOD="2014-Q2" OBS_VALUE="12.2"/><Obs TIME_PERIOD="2014-Q3" OBS_VALUE="11.6"/><Obs TIME_PERIOD="2014-Q4" OBS_VALUE="10.9"/><Obs TIME_PERIOD="2015-Q1" OBS_VALUE="10.7"/><Obs TIME_PERIOD="2015-Q2" OBS_VALUE="9.9"/><Obs TIME_PERIOD="2015-Q3" OBS_VALUE="9.6"/><Obs TIME_PERIOD="2015-Q4" OBS_VALUE="9.5"/><Obs TIME_PERIOD="2016-Q1" OBS_VALUE="9.0"/><Obs TIME_PERIOD="2016-Q2" OBS_VALUE="8.7"/><Obs TIME_PERIOD="2016-Q3" OBS_VALUE="8.2"/><Obs TIME_PERIOD="2016-Q4" OBS_VALUE="7.6"/><Obs TIME_PERIOD="2017-Q1" OBS_VALUE="7.2"/><Obs TIME_PERIOD="2017-Q2" OBS_VALUE="6.8"/><Obs TIME_PERIOD="2017-Q3" OBS_VALUE="6.6"/><Obs TIME_PERIOD="2017-Q4" OBS_VALUE="6.4"/><Obs TIME_PERIOD="2018-Q1" OBS_VALUE="6.0"/><Obs TIME_PERIOD="2018-Q2" OBS_VALUE="5.9"/><Obs TIME_PERIOD="2018-Q3" OBS_VALUE="5.7"/><Obs TIME_PERIOD="2018-Q4" OBS_VALUE="5.5"/><Obs TIME_PERIOD="2019-Q1" OBS_VALUE="5.1"/><Obs TIME_PERIOD="2019-Q2" OBS_VALUE="5.2"/><Obs TIME_PERIOD="2019-Q3" OBS_VALUE="5.0"/><Obs TIME_PERIOD="2019-Q4" OBS_VALUE="4.8"/><Obs TIME_PERIOD="2020-Q1" OBS_VALUE="4.8"/><Obs TIME_PERIOD="2020-Q2" OBS_VALUE="5.3"/><Obs TIME_PERIOD="2020-Q3" OBS_VALUE="7.0"/><Obs TIME_PERIOD="2020-Q4" OBS_VALUE="6.4"/><Obs TIME_PERIOD="2021-Q1" OBS_VALUE="7.1" OBS_FLAG="b"/><Obs TIME_PERIOD="2021-Q2" OBS_VALUE="7.1"/><Obs TIME_PERIOD="2021-Q3" OBS_VALUE="5.5"/><Obs TIME_PERIOD="2021-Q4" OBS_VALUE="5.2"/><Obs TIME_PERIOD="2022-Q1" OBS_VALUE="4.8"/><Obs TIME_PERIOD="2022-Q2" OBS_VALUE="4.4"/><Obs TIME_PERIOD="2022-Q3" OBS_VALUE="4.2"/><Obs TIME_PERIOD="2022-Q4" OBS_VALUE="4.3"/><Obs TIME_PERIOD="2023-Q1" OBS_VALUE="4.2"/><Obs TIME_PERIOD="2023-Q2" OBS_VALUE="4.3"/><Obs TIME_PERIOD="2023-Q3" OBS_VALUE="4.4"/><Obs TIME_PERIOD="2023-Q4" OBS_VALUE="4.3"/></Series><Series age="Y15-74" freq="Q" geo="IS" sex="T" s_adj="SA" unit="PC_ACT"><Obs TIME_PERIOD="2010-Q1" OBS_VALUE="7.6"/><Obs TIME_PERIOD="2010-Q2" OBS_VALUE="7.5"/><Obs TIME_PERIOD="2010-Q3" OBS_VALUE="7.4"/><Obs TIME_PERIOD="2010-Q4" OBS_VALUE="7.8"/><Obs TIME_PERIOD="2011-Q1" OBS_VALUE="7.6"/><Obs TIME_PERIOD="2011-Q2" OBS_VALUE="7.2"/><Obs TIME_PERIOD="2011-Q3" OBS_VALUE="6.8"/><Obs TIME_PERIOD="2011-Q4" OBS_VALUE="6.7"/><Obs TIME_PERIOD="2012-Q1" OBS_VALUE="6.7"/><Obs TIME_PERIOD="2012-Q2" OBS_VALUE="6.0"/><Obs TIME_PERIOD="2012-Q3" OBS_VALUE="5.9"/><Obs TIME_PERIOD="2012-Q4" OBS_VALUE="5.5"/><Obs TIME_PERIOD="2013-Q1" OBS_VALUE="5.6"/><Obs TIME_PERIOD="2013-Q2" OBS_VALUE="5.7"/><Obs TIME_PERIOD="2013-Q3" OBS_VALUE="5.2"/><Obs TIME_PERIOD="2013-Q4" OBS_VALUE="5.0"/><Obs TIME_PERIOD="2014-Q1" OBS_VALUE="5.5"/><Obs TIME_PERIOD="2014-Q2" OBS_VALUE="4.9"/><Obs TIME_PERIOD="2014-Q3" OBS_VALUE="4.7"/><Obs TIME_PERIOD="2014-Q4" OBS_VALUE="4.8"/><Obs TIME_PERIOD="2015-Q1" OBS_VALUE="4.2"/><Obs TIME_PERIOD="2015-Q2" OBS_VALUE="4.1"/><Obs TIME_PERIOD="2015-Q3" OBS_VALUE="4.0"/><Obs TIME_PERIOD="2015-Q4" OBS_VALUE="3.7"/><Obs TIME_PERIOD="2016-Q1" OBS_VALUE="3.2"/><Obs TIME_PERIOD="2016-Q2" OBS_VALUE="2.9"/><Obs TIME_PERIOD="2016-Q3" OBS_VALUE="3.0"/><Obs TIME_PERIOD="2016-Q4" OBS_VALUE="2.8"/><Obs TIME_PERIOD="2017-Q1" OBS_VALUE="2.8"/><Obs TIME_PERIOD="2017-Q2" OBS_VALUE="2.8"/><Obs TIME_PERIOD="2017-Q3" OBS_VALUE="2.8"/><Obs TIME_PERIOD="2017-Q4" OBS_VALUE="2.8"/><Obs TIME_PERIOD="2018-Q1" OBS_VALUE="2.7"/><Obs TIME_PERIOD="2018-Q2" OBS_VALUE="2.7"/><Obs TIME_PERIOD="2018-Q3" OBS_VALUE="2.6"/><Obs TIME_PERIOD="2018-Q4" OBS_VALUE="2.7"/><Obs TIME_PERIOD="2019-Q1" OBS_VALUE="3.1"/><Obs TIME_PERIOD="2019-Q2" OBS_VALUE="3.2"/><Obs TIME_PERIOD="2019-Q3" OBS_VALUE="3.8"/><Obs TIME_PERIOD="2019-Q4" OBS_VALUE="3.8"/><Obs TIME_PERIOD="2020-Q1" OBS_VALUE="3.5"/><Obs TIME_PERIOD="2020-Q2" OBS_VALUE="5.1"/><Obs TIME_PERIOD="2020-Q3" OBS_VALUE="5.5"/><Obs TIME_PERIOD="2020-Q4" OBS_VALUE="7.8" OBS_FLAG="b"/><Obs TIME_PERIOD="2021-Q1" OBS_VALUE="7.7"/><Obs TIME_PERIOD="2021-Q2" OBS_VALUE="6.9"/><Obs TIME_PERIOD="2021-Q3" OBS_VALUE="4.7"/><Obs TIME_PERIOD="2021-Q4" OBS_VALUE="4.7"/><Obs TIME_PERIOD="2022-Q1" OBS_VALUE="4.1"/><Obs TIME_PERIOD="2022-Q2" OBS_VALUE="3.8"/><Obs TIME_PERIOD="2022-Q3" OBS_VALUE="3.7"/><Obs TIME_PERIOD="2022-Q4" OBS_VALUE="3.4"/><Obs TIME_PERIOD="2023-Q1" OBS_VALUE="3.7"/><Obs TIME_PERIOD="2023-Q2" OBS_VALUE="3.3"/><Obs TIME_PERIOD="2023-Q3" OBS_VALUE="3.8"/><Obs TIME_PERIOD="2023-Q4" OBS_VALUE="3.4"/></Series><Series age="Y15-74" freq="Q" geo="IT" sex="T" s_adj="SA" unit="PC_ACT"><Obs TIME_PERIOD="2010-Q1" OBS_VALUE="8.5"/><Obs TIME_PERIOD="2010-Q2" OBS_VALUE="8.7"/><Obs TIME_PERIOD="2010-Q3" OBS_VALUE="8.5"/><Obs TIME_PERIOD="2010-Q4" OBS_VALUE="8.4"/><Obs TIME_PERIOD="2011-Q1" OBS_VALUE="8.1"/><Obs TIME_PERIOD="2011-Q2" OBS_VALUE="8.2"/><Obs TIME_PERIOD="2011-Q3" OBS_VALUE="8.7"/><Obs TIME_PERIOD="2011-Q4" OBS_VALUE="9.4"/><Obs TIME_PERIOD="2012-Q1" OBS_VALUE="10.3"/><Obs TIME_PERIOD="2012-Q2" OBS_VALUE="10.9"/><Obs TIME_PERIOD="2012-Q3" OBS_VALUE="10.9"/><Obs TIME_PERIOD="2012-Q4" OBS_VALUE="11.5"/><Obs TIME_PERIOD="2013-Q1" OBS_VALUE="12.1"/><Obs TIME_PERIOD="2013-Q2" OBS_VALUE="12.4"/><Obs TIME_PERIOD="2013-Q3" OBS_VALUE="12.4"/><Obs TIME_PERIOD="2013-Q4" OBS_VALUE="12.5"/><Obs TIME_PERIOD="2014-Q1" OBS_VALUE="13.0"/><Obs TIME_PERIOD="2014-Q2" OBS_VALUE="12.6"/><Obs TIME_PERIOD="2014-Q3" OBS_VALUE="12.8"/><Obs TIME_PERIOD="2014-Q4" OBS_VALUE="12.9"/><Obs TIME_PERIOD="2015-Q1" OBS_VALUE="12.4"/><Obs TIME_PERIOD="2015-Q2" OBS_VALUE="12.4"/><Obs TIME_PERIOD="2015-Q3" OBS_VALUE="11.6"/><Obs TIME_PERIOD="2015-Q4" OBS_VALUE="11.7"/><Obs TIME_PERIOD="2016-Q1" OBS_VALUE="11.5"/><Obs TIME_PERIOD="2016-Q2" OBS_VALUE="11.7"/><Obs TIME_PERIOD="2016-Q3" OBS_VALUE="11.8"/><Obs TIME_PERIOD="2016-Q4" OBS_VALUE="11.9"/><Obs TIME_PERIOD="2017-Q1" OBS_VALUE="11.5"/><Obs TIME_PERIOD="2017-Q2" OBS_VALUE="11.2"/><Obs TIME_PERIOD="2017-Q3" OBS_VALUE="11.4"/><Obs TIME_PERIOD="2017-Q4" OBS_VALUE="10.9"/><Obs TIME_PERIOD="2018-Q1" OBS_VALUE="10.8" OBS_FLAG="b"/><Obs TIME_PERIOD="2018-Q2" OBS_VALUE="10.9"/><Obs TIME_PERIOD="2018-Q3" OBS_VALUE="10.1"/><Obs TIME_PERIOD="2018-Q4" OBS_VALUE="10.5"/><Obs TIME_PERIOD="2019-Q1" OBS_VALUE="10.4"/><Obs TIME_PERIOD="2019-Q2" OBS_VALUE="10.0"/><Obs TIME_PERIOD="2019-Q3" OBS_VALUE="9.7"/><Obs TIME_PERIOD="2019-Q4" OBS_VALUE="9.6"/><Obs TIME_PERIOD="2020-Q1" OBS_VALUE="9.0"/><Obs TIME_PERIOD="2020-Q2" OBS_VALUE="8.1"/><Obs TIME_PERIOD="2020-Q3" OBS_VALUE="10.7"/><Obs TIME_PERIOD="2020-Q4" OBS_VALUE="9.6"/><Obs TIME_PERIOD="2021-Q1" OBS_VALUE="10.1"/><Obs TIME_PERIOD="2021-Q2" OBS_VALUE="9.8"/><Obs TIME_PERIOD="2021-Q3" OBS_VALUE="9.3"/><Obs TIME_PERIOD="2021-Q4" OBS_VALUE="9.0"/><Obs TIME_PERIOD="2022-Q1" OBS_VALUE="8.2"/><Obs TIME_PERIOD="2022-Q2" OBS_VALUE="8.2"/><Obs TIME_PERIOD="2022-Q3" OBS_VALUE="8.2"/><Obs TIME_PERIOD="2022-Q4" OBS_VALUE="7.8"/><Obs TIME_PERIOD="2023-Q1" OBS_VALUE="7.7"/><Obs TIME_PERIOD="2023-Q2" OBS_VALUE="7.7"/><Obs TIME_PERIOD="2023-Q3" OBS_VALUE="7.7"/><Obs TIME_PERIOD="2023-Q4" OBS_VALUE="7.5"/></Series><Series age="Y15-74" freq="Q" geo="LT" sex="T" s_adj="SA" unit="PC_ACT"><Obs TIME_PERIOD="2010-Q1" OBS_VALUE="17.7"/><Obs TIME_PERIOD="2010-Q2" OBS_VALUE="18.0"/><Obs TIME_PERIOD="2010-Q3" OBS_VALUE="18.0"/><Obs TIME_PERIOD="2010-Q4" OBS_VALUE="17.6"/><Obs TIME_PERIOD="2011-Q1" OBS_VALUE="16.7"/><Obs TIME_PERIOD="2011-Q2" OBS_VALUE="15.5"/><Obs TIME_PERIOD="2011-Q3" OBS_VALUE="15.2"/><Obs TIME_PERIOD="2011-Q4" OBS_VALUE="14.2"/><Obs TIME_PERIOD="2012-Q1" OBS_VALUE="14.2"/><Obs TIME_PERIOD="2012-Q2" OBS_VALUE="13.2"/><Obs TIME_PERIOD="2012-Q3" OBS_VALUE="12.9"/><Obs TIME_PERIOD="2012-Q4" OBS_VALUE="13.3"/><Obs TIME_PERIOD="2013-Q1" OBS_VALUE="12.6"/><Obs TIME_PERIOD="2013-Q2" OBS_VALUE="11.6"/><Obs TIME_PERIOD="2013-Q3" OBS_VALUE="11.5"/><Obs TIME_PERIOD="2013-Q4" OBS_VALUE="11.6"/><Obs TIME_PERIOD="2014-Q1" OBS_VALUE="11.9"/><Obs TIME_PERIOD="2014-Q2" OBS_VALUE="11.0"/><Obs TIME_PERIOD="2014-Q3" OBS_VALUE="9.6"/><Obs TIME_PERIOD="2014-Q4" OBS_VALUE="10.2"/><Obs TIME_PERIOD="2015-Q1" OBS_VALUE="9.8"/><Obs TIME_PERIOD="2015-Q2" OBS_VALUE="9.2"/><Obs TIME_PERIOD="2015-Q3" OBS_VALUE="8.6"/><Obs TIME_PERIOD="2015-Q4" OBS_VALUE="8.8"/><Obs TIME_PERIOD="2016-Q1" OBS_VALUE="8.2"/><Obs TIME_PERIOD="2016-Q2" OBS_VALUE="8.0"/><Obs TIME_PERIOD="2016-Q3" OBS_VALUE="7.8"/><Obs TIME_PERIOD="2016-Q4" OBS_VALUE="7.8"/><Obs TIME_PERIOD="2017-Q1" OBS_VALUE="7.7"/><Obs TIME_PERIOD="2017-Q2" OBS_VALUE="7.0"/><Obs TIME_PERIOD="2017-Q3" OBS_VALUE="6.9"/><Obs TIME_PERIOD="2017-Q4" OBS_VALUE="6.8"/><Obs TIME_PERIOD="2018-Q1" OBS_VALUE="6.8"/><Obs TIME_PERIOD="2018-Q2" OBS_VALUE="6.0"/><Obs TIME_PERIOD="2018-Q3" OBS_VALUE="5.8"/><Obs TIME_PERIOD="2018-Q4" OBS_VALUE="6.1"/><Obs TIME_PERIOD="2019-Q1" OBS_VALUE="6.3"/><Obs TIME_PERIOD="2019-Q2" OBS_VALUE="6.1"/><Obs TIME_PERIOD="2019-Q3" OBS_VALUE="6.1"/><Obs TIME_PERIOD="2019-Q4" OBS_VALUE="6.5"/><Obs TIME_PERIOD="2020-Q1" OBS_VALUE="7.2"/><Obs TIME_PERIOD="2020-Q2" OBS_VALUE="8.5"/><Obs TIME_PERIOD="2020-Q3" OBS_VALUE="9.2"/><Obs TIME_PERIOD="2020-Q4" OBS_VALUE="8.9"/><Obs TIME_PERIOD="2021-Q1" OBS_VALUE="7.7"/><Obs TIME_PERIOD="2021-Q2" OBS_VALUE="7.6"/><Obs TIME_PERIOD="2021-Q3" OBS_VALUE="6.7"/><Obs TIME_PERIOD="2021-Q4" OBS_VALUE="6.6"/><Obs TIME_PERIOD="2022-Q1" OBS_VALUE="6.4"/><Obs TIME_PERIOD="2022-Q2" OBS_VALUE="5.6"/><Obs TIME_PERIOD="2022-Q3" OBS_VALUE="6.0"/><Obs TIME_PERIOD="2022-Q4" OBS_VALUE="6.2"/><Obs TIME_PERIOD="2023-Q1" OBS_VALUE="7.6"/><Obs TIME_PERIOD="2023-Q2" OBS_VALUE="6.2"/><Obs TIME_PERIOD="2023-Q3" OBS_VALUE="6.4"/><Obs TIME_PERIOD="2023-Q4" OBS_VALUE="7.4"/></Series><Series age="Y15-74" freq="Q" geo="LU" sex="T" s_adj="SA" unit="PC_ACT"><Obs TIME_PERIOD="2010-Q1" OBS_VALUE="5.0"/><Obs TIME_PERIOD="2010-Q2" OBS_VALUE="4.2"/><Obs TIME_PERIOD="2010-Q3" OBS_VALUE="3.7"/><Obs TIME_PERIOD="2010-Q4" OBS_VALUE="4.5"/><Obs TIME_PERIOD="2011-Q1" OBS_VALUE="5.3"/><Obs TIME_PERIOD="2011-Q2" OBS_VALUE="5.4"/><Obs TIME_PERIOD="2011-Q3" OBS_VALUE="4.2"/><Obs TIME_PERIOD="2011-Q4" OBS_VALUE="4.7"/><Obs TIME_PERIOD="2012-Q1" OBS_VALUE="6.0"/><Obs TIME_PERIOD="2012-Q2" OBS_VALUE="4.1"/><Obs TIME_PERIOD="2012-Q3" OBS_VALUE="5.5"/><Obs TIME_PERIOD="2012-Q4" OBS_VALUE="5.0"/><Obs TIME_PERIOD="2013-Q1" OBS_VALUE="5.6"/><Obs TIME_PERIOD="2013-Q2" OBS_VALUE="6.3"/><Obs TIME_PERIOD="2013-Q3" OBS_VALUE="5.4"/><Obs TIME_PERIOD="2013-Q4" OBS_VALUE="6.1"/><Obs TIME_PERIOD="2014-Q1" OBS_VALUE="6.7"/><Obs TIME_PERIOD="2014-Q2" OBS_VALUE="5.1"/><Obs TIME_PERIOD="2014-Q3" OBS_VALUE="6.2"/><Obs TIME_PERIOD="2014-Q4" OBS_VALUE="5.5"/><Obs TIME_PERIOD="2015-Q1" OBS_VALUE="7.4" OBS_FLAG="b"/><Obs TIME_PERIOD="2015-Q2" OBS_VALUE="5.5"/><Obs TIME_PERIOD="2015-Q3" OBS_VALUE="7.5"/><Obs TIME_PERIOD="2015-Q4" OBS_VALUE="6.2"/><Obs TIME_PERIOD="2016-Q1" OBS_VALUE="6.0"/><Obs TIME_PERIOD="2016-Q2" OBS_VALUE="6.2"/><Obs TIME_PERIOD="2016-Q3" OBS_VALUE="6.9"/><Obs TIME_PERIOD="2016-Q4" OBS_VALUE="5.9"/><Obs TIME_PERIOD="2017-Q1" OBS_VALUE="6.2"/><Obs TIME_PERIOD="2017-Q2" OBS_VALUE="5.4"/><Obs TIME_PERIOD="2017-Q3" OBS_VALUE="5.4"/><Obs TIME_PERIOD="2017-Q4" OBS_VALUE="5.2"/><Obs TIME_PERIOD="2018-Q1" OBS_VALUE="5.7"/><Obs TIME_PERIOD="2018-Q2" OBS_VALUE="5.6"/><Obs TIME_PERIOD="2018-Q3" OBS_VALUE="5.9"/><Obs TIME_PERIOD="2018-Q4" OBS_VALUE="5.2"/><Obs TIME_PERIOD="2019-Q1" OBS_VALUE="5.5"/><Obs TIME_PERIOD="2019-Q2" OBS_VALUE="5.4"/><Obs TIME_PERIOD="2019-Q3" OBS_VALUE="5.7"/><Obs TIME_PERIOD="2019-Q4" OBS_VALUE="5.8"/><Obs TIME_PERIOD="2020-Q1" OBS_VALUE="6.4"/><Obs TIME_PERIOD="2020-Q2" OBS_VALUE="6.5"/><Obs TIME_PERIOD="2020-Q3" OBS_VALUE="7.7"/><Obs TIME_PERIOD="2020-Q4" OBS_VALUE="6.6"/><Obs TIME_PERIOD="2021-Q1" OBS_VALUE="5.6"/><Obs TIME_PERIOD="2021-Q2" OBS_VALUE="5.7"/><Obs TIME_PERIOD="2021-Q3" OBS_VALUE="5.4"/><Obs TIME_PERIOD="2021-Q4" OBS_VALUE="4.3"/><Obs TIME_PERIOD="2022-Q1" OBS_VALUE="4.2"/><Obs TIME_PERIOD="2022-Q2" OBS_VALUE="4.6"/><Obs TIME_PERIOD="2022-Q3" OBS_VALUE="5.0"/><Obs TIME_PERIOD="2022-Q4" OBS_VALUE="4.6"/><Obs TIME_PERIOD="2023-Q1" OBS_VALUE="5.0"/><Obs TIME_PERIOD="2023-Q2" OBS_VALUE="5.0"/><Obs TIME_PERIOD="2023-Q3" OBS_VALUE="5.3"/><Obs TIME_PERIOD="2023-Q4" OBS_VALUE="5.4"/></Series><Series age="Y15-74" freq="Q" geo="LV" sex="T" s_adj="SA" unit="PC_ACT"><Obs TIME_PERIOD="2010-Q1" OBS_VALUE="20.7"/><Obs TIME_PERIOD="2010-Q2" OBS_VALUE="20.3"/><Obs TIME_PERIOD="2010-Q3" OBS_VALUE="19.2"/><Obs TIME_PERIOD="2010-Q4" OBS_VALUE="18.4"/><Obs TIME_PERIOD="2011-Q1" OBS_VALUE="17.3"/><Obs TIME_PERIOD="2011-Q2" OBS_VALUE="16.9"/><Obs TIME_PERIOD="2011-Q3" OBS_VALUE="15.6"/><Obs TIME_PERIOD="2011-Q4" OBS_VALUE="15.4"/><Obs TIME_PERIOD="2012-Q1" OBS_VALUE="15.8"/><Obs TIME_PERIOD="2012-Q2" OBS_VALUE="16.4"/><Obs TIME_PERIOD="2012-Q3" OBS_VALUE="14.2"/><Obs TIME_PERIOD="2012-Q4" OBS_VALUE="13.9"/><Obs TIME_PERIOD="2013-Q1" OBS_VALUE="12.5"/><Obs TIME_PERIOD="2013-Q2" OBS_VALUE="11.7"/><Obs TIME_PERIOD="2013-Q3" OBS_VALUE="12.3"/><Obs TIME_PERIOD="2013-Q4" OBS_VALUE="11.5"/><Obs TIME_PERIOD="2014-Q1" OBS_VALUE="11.3"/><Obs TIME_PERIOD="2014-Q2" OBS_VALUE="10.5"/><Obs TIME_PERIOD="2014-Q3" OBS_VALUE="10.9"/><Obs TIME_PERIOD="2014-Q4" OBS_VALUE="10.5"/><Obs TIME_PERIOD="2015-Q1" OBS_VALUE="10.1"/><Obs TIME_PERIOD="2015-Q2" OBS_VALUE="9.6"/><Obs TIME_PERIOD="2015-Q3" OBS_VALUE="9.8"/><Obs TIME_PERIOD="2015-Q4" OBS_VALUE="10.0"/><Obs TIME_PERIOD="2016-Q1" OBS_VALUE="10.2"/><Obs TIME_PERIOD="2016-Q2" OBS_VALUE="9.7"/><Obs TIME_PERIOD="2016-Q3" OBS_VALUE="9.6"/><Obs TIME_PERIOD="2016-Q4" OBS_VALUE="9.4"/><Obs TIME_PERIOD="2017-Q1" OBS_VALUE="9.2"/><Obs TIME_PERIOD="2017-Q2" OBS_VALUE="8.7"/><Obs TIME_PERIOD="2017-Q3" OBS_VALUE="8.7"/><Obs TIME_PERIOD="2017-Q4" OBS_VALUE="8.5"/><Obs TIME_PERIOD="2018-Q1" OBS_VALUE="8.1"/><Obs TIME_PERIOD="2018-Q2" OBS_VALUE="7.4"/><Obs TIME_PERIOD="2018-Q3" OBS_VALUE="7.0"/><Obs TIME_PERIOD="2018-Q4" OBS_VALUE="7.2"/><Obs TIME_PERIOD="2019-Q1" OBS_VALUE="6.9"/><Obs TIME_PERIOD="2019-Q2" OBS_VALUE="6.2"/><Obs TIME_PERIOD="2019-Q3" OBS_VALUE="6.0"/><Obs TIME_PERIOD="2019-Q4" OBS_VALUE="6.2"/><Obs TIME_PERIOD="2020-Q1" OBS_VALUE="7.8"/><Obs TIME_PERIOD="2020-Q2" OBS_VALUE="8.4"/><Obs TIME_PERIOD="2020-Q3" OBS_VALUE="8.2"/><Obs TIME_PERIOD="2020-Q4" OBS_VALUE="8.1"/><Obs TIME_PERIOD="2021-Q1" OBS_VALUE="8.1"/><Obs TIME_PERIOD="2021-Q2" OBS_VALUE="7.7"/><Obs TIME_PERIOD="2021-Q3" OBS_VALUE="7.2"/><Obs TIME_PERIOD="2021-Q4" OBS_VALUE="7.4"/><Obs TIME_PERIOD="2022-Q1" OBS_VALUE="7.1"/><Obs TIME_PERIOD="2022-Q2" OBS_VALUE="6.5"/><Obs TIME_PERIOD="2022-Q3" OBS_VALUE="7.0"/><Obs TIME_PERIOD="2022-Q4" OBS_VALUE="6.9"/><Obs TIME_PERIOD="2023-Q1" OBS_VALUE="6.3"/><Obs TIME_PERIOD="2023-Q2" OBS_VALUE="6.2"/><Obs TIME_PERIOD="2023-Q3" OBS_VALUE="6.4"/><Obs TIME_PERIOD="2023-Q4" OBS_VALUE="7.0"/></Series><Series age="Y15-74" freq="Q" geo="ME" sex="T" s_adj="SA" unit="PC_ACT"><Obs TIME_PERIOD="2011-Q1" OBS_VALUE="20.9"/><Obs TIME_PERIOD="2011-Q2" OBS_VALUE="20.1"/><Obs TIME_PERIOD="2011-Q3" OBS_VALUE="20.0"/><Obs TIME_PERIOD="2011-Q4" OBS_VALUE="17.8"/><Obs TIME_PERIOD="2012-Q1" OBS_VALUE="20.5"/><Obs TIME_PERIOD="2012-Q2" OBS_VALUE="20.2"/><Obs TIME_PERIOD="2012-Q3" OBS_VALUE="19.0"/><Obs TIME_PERIOD="2012-Q4" OBS_VALUE="20.3"/><Obs TIME_PERIOD="2013-Q1" OBS_VALUE="21.2"/><Obs TIME_PERIOD="2013-Q2" OBS_VALUE="19.4"/><Obs TIME_PERIOD="2013-Q3" OBS_VALUE="18.2"/><Obs TIME_PERIOD="2013-Q4" OBS_VALUE="19.2"/><Obs TIME_PERIOD="2014-Q1" OBS_VALUE="18.9"/><Obs TIME_PERIOD="2014-Q2" OBS_VALUE="18.7"/><Obs TIME_PERIOD="2014-Q3" OBS_VALUE="16.8"/><Obs TIME_PERIOD="2014-Q4" OBS_VALUE="17.8"/><Obs TIME_PERIOD="2015-Q1" OBS_VALUE="17.9"/><Obs TIME_PERIOD="2015-Q2" OBS_VALUE="17.9"/><Obs TIME_PERIOD="2015-Q3" OBS_VALUE="16.9"/><Obs TIME_PERIOD="2015-Q4" OBS_VALUE="17.6"/><Obs TIME_PERIOD="2016-Q1" OBS_VALUE="18.8"/><Obs TIME_PERIOD="2016-Q2" OBS_VALUE="17.7"/><Obs TIME_PERIOD="2016-Q3" OBS_VALUE="17.3"/><Obs TIME_PERIOD="2016-Q4" OBS_VALUE="17.2"/><Obs TIME_PERIOD="2017-Q1" OBS_VALUE="17.2"/><Obs TIME_PERIOD="2017-Q2" OBS_VALUE="15.3"/><Obs TIME_PERIOD="2017-Q3" OBS_VALUE="15.2"/><Obs TIME_PERIOD="2017-Q4" OBS_VALUE="16.8"/><Obs TIME_PERIOD="2018-Q1" OBS_VALUE="16.0"/><Obs TIME_PERIOD="2018-Q2" OBS_VALUE="14.6"/><Obs TIME_PERIOD="2018-Q3" OBS_VALUE="14.5"/><Obs TIME_PERIOD="2018-Q4" OBS_VALUE="15.8"/><Obs TIME_PERIOD="2019-Q1" OBS_VALUE="14.9"/><Obs TIME_PERIOD="2019-Q2" OBS_VALUE="14.5"/><Obs TIME_PERIOD="2019-Q3" OBS_VALUE="15.6"/><Obs TIME_PERIOD="2019-Q4" OBS_VALUE="15.6"/><Obs TIME_PERIOD="2020-Q1" OBS_VALUE="16.2"/><Obs TIME_PERIOD="2020-Q2" OBS_VALUE="15.4"/><Obs TIME_PERIOD="2020-Q3" OBS_VALUE="19.4"/><Obs TIME_PERIOD="2020-Q4" OBS_VALUE="20.8"/></Series><Series age="Y15-74" freq="Q" geo="MK" sex="T" s_adj="SA" unit="PC_ACT"><Obs TIME_PERIOD="2010-Q1" OBS_VALUE="33.5"/><Obs TIME_PERIOD="2010-Q2" OBS_VALUE="32.1"/><Obs TIME_PERIOD="2010-Q3" OBS_VALUE="31.7"/><Obs TIME_PERIOD="2010-Q4" OBS_VALUE="31.0"/><Obs TIME_PERIOD="2011-Q1" OBS_VALUE="31.2"/><Obs TIME_PERIOD="2011-Q2" OBS_VALUE="31.4"/><Obs TIME_PERIOD="2011-Q3" OBS_VALUE="31.2"/><Obs TIME_PERIOD="2011-Q4" OBS_VALUE="31.8"/><Obs TIME_PERIOD="2012-Q1" OBS_VALUE="31.6"/><Obs TIME_PERIOD="2012-Q2" OBS_VALUE="31.3"/><Obs TIME_PERIOD="2012-Q3" OBS_VALUE="30.7"/><Obs TIME_PERIOD="2012-Q4" OBS_VALUE="30.6"/><Obs TIME_PERIOD="2013-Q1" OBS_VALUE="29.9"/><Obs TIME_PERIOD="2013-Q2" OBS_VALUE="28.8"/><Obs TIME_PERIOD="2013-Q3" OBS_VALUE="28.7"/><Obs TIME_PERIOD="2013-Q4" OBS_VALUE="28.7"/><Obs TIME_PERIOD="2014-Q1" OBS_VALUE="28.4"/><Obs TIME_PERIOD="2014-Q2" OBS_VALUE="28.2"/><Obs TIME_PERIOD="2014-Q3" OBS_VALUE="27.9"/><Obs TIME_PERIOD="2014-Q4" OBS_VALUE="27.6"/><Obs TIME_PERIOD="2015-Q1" OBS_VALUE="27.4"/><Obs TIME_PERIOD="2015-Q2" OBS_VALUE="26.9"/><Obs TIME_PERIOD="2015-Q3" OBS_VALUE="25.5"/><Obs TIME_PERIOD="2015-Q4" OBS_VALUE="24.7"/><Obs TIME_PERIOD="2016-Q1" OBS_VALUE="24.5"/><Obs TIME_PERIOD="2016-Q2" OBS_VALUE="24.0"/><Obs TIME_PERIOD="2016-Q3" OBS_VALUE="23.4"/><Obs TIME_PERIOD="2016-Q4" OBS_VALUE="23.1"/><Obs TIME_PERIOD="2017-Q1" OBS_VALUE="23.0"/><Obs TIME_PERIOD="2017-Q2" OBS_VALUE="22.6"/><Obs TIME_PERIOD="2017-Q3" OBS_VALUE="22.1"/><Obs TIME_PERIOD="2017-Q4" OBS_VALUE="21.9"/><Obs TIME_PERIOD="2018-Q1" OBS_VALUE="21.6"/><Obs TIME_PERIOD="2018-Q2" OBS_VALUE="21.2"/><Obs TIME_PERIOD="2018-Q3" OBS_VALUE="20.8"/><Obs TIME_PERIOD="2018-Q4" OBS_VALUE="19.4"/><Obs TIME_PERIOD="2019-Q1" OBS_VALUE="17.9"/><Obs TIME_PERIOD="2019-Q2" OBS_VALUE="17.5"/><Obs TIME_PERIOD="2019-Q3" OBS_VALUE="17.1"/><Obs TIME_PERIOD="2019-Q4" OBS_VALUE="16.6"/><Obs TIME_PERIOD="2020-Q1" OBS_VALUE="16.2"/><Obs TIME_PERIOD="2020-Q2" OBS_VALUE="16.8"/><Obs TIME_PERIOD="2020-Q3" OBS_VALUE="16.5"/><Obs TIME_PERIOD="2020-Q4" OBS_VALUE="16.2"/></Series><Series age="Y15-74" freq="Q" geo="MT" sex="T" s_adj="SA" unit="PC_ACT"><Obs TIME_PERIOD="2010-Q1" OBS_VALUE="7.1"/><Obs TIME_PERIOD="2010-Q2" OBS_VALUE="6.7"/><Obs TIME_PERIOD="2010-Q3" OBS_VALUE="6.6"/><Obs TIME_PERIOD="2010-Q4" OBS_VALUE="7.1"/><Obs TIME_PERIOD="2011-Q1" OBS_VALUE="6.6"/><Obs TIME_PERIOD="2011-Q2" OBS_VALUE="6.7"/><Obs TIME_PERIOD="2011-Q3" OBS_VALUE="5.9"/><Obs TIME_PERIOD="2011-Q4" OBS_VALUE="6.4"/><Obs TIME_PERIOD="2012-Q1" OBS_VALUE="6.2"/><Obs TIME_PERIOD="2012-Q2" OBS_VALUE="6.3"/><Obs TIME_PERIOD="2012-Q3" OBS_VALUE="6.3"/><Obs TIME_PERIOD="2012-Q4" OBS_VALUE="6.0"/><Obs TIME_PERIOD="2013-Q1" OBS_VALUE="5.8"/><Obs TIME_PERIOD="2013-Q2" OBS_VALUE="6.4"/><Obs TIME_PERIOD="2013-Q3" OBS_VALUE="6.2"/><Obs TIME_PERIOD="2013-Q4" OBS_VALUE="6.0"/><Obs TIME_PERIOD="2014-Q1" OBS_VALUE="5.8"/><Obs TIME_PERIOD="2014-Q2" OBS_VALUE="5.9"/><Obs TIME_PERIOD="2014-Q3" OBS_VALUE="5.9"/><Obs TIME_PERIOD="2014-Q4" OBS_VALUE="5.4"/><Obs TIME_PERIOD="2015-Q1" OBS_VALUE="5.4"/><Obs TIME_PERIOD="2015-Q2" OBS_VALUE="5.6"/><Obs TIME_PERIOD="2015-Q3" OBS_VALUE="5.2"/><Obs TIME_PERIOD="2015-Q4" OBS_VALUE="5.3"/><Obs TIME_PERIOD="2016-Q1" OBS_VALUE="5.2"/><Obs TIME_PERIOD="2016-Q2" OBS_VALUE="5.0"/><Obs TIME_PERIOD="2016-Q3" OBS_VALUE="4.3"/><Obs TIME_PERIOD="2016-Q4" OBS_VALUE="4.3"/><Obs TIME_PERIOD="2017-Q1" OBS_VALUE="4.1"/><Obs TIME_PERIOD="2017-Q2" OBS_VALUE="3.9"/><Obs TIME_PERIOD="2017-Q3" OBS_VALUE="4.0"/><Obs TIME_PERIOD="2017-Q4" OBS_VALUE="4.0"/><Obs TIME_PERIOD="2018-Q1" OBS_VALUE="4.3"/><Obs TIME_PERIOD="2018-Q2" OBS_VALUE="4.1"/><Obs TIME_PERIOD="2018-Q3" OBS_VALUE="3.7"/><Obs TIME_PERIOD="2018-Q4" OBS_VALUE="3.8"/><Obs TIME_PERIOD="2019-Q1" OBS_VALUE="4.2"/><Obs TIME_PERIOD="2019-Q2" OBS_VALUE="4.0"/><Obs TIME_PERIOD="2019-Q3" OBS_VALUE="4.1"/><Obs TIME_PERIOD="2019-Q4" OBS_VALUE="4.0"/><Obs TIME_PERIOD="2020-Q1" OBS_VALUE="4.0"/><Obs TIME_PERIOD="2020-Q2" OBS_VALUE="5.0"/><Obs TIME_PERIOD="2020-Q3" OBS_VALUE="5.4"/><Obs TIME_PERIOD="2020-Q4" OBS_VALUE="5.1"/><Obs TIME_PERIOD="2021-Q1" OBS_VALUE="4.2"/><Obs TIME_PERIOD="2021-Q2" OBS_VALUE="3.8"/><Obs TIME_PERIOD="2021-Q3" OBS_VALUE="3.7"/><Obs TIME_PERIOD="2021-Q4" OBS_VALUE="3.4"/><Obs TIME_PERIOD="2022-Q1" OBS_VALUE="3.6"/><Obs TIME_PERIOD="2022-Q2" OBS_VALUE="3.8"/><Obs TIME_PERIOD="2022-Q3" OBS_VALUE="3.3"/><Obs TIME_PERIOD="2022-Q4" OBS_VALUE="3.3"/><Obs TIME_PERIOD="2023-Q1" OBS_VALUE="3.5"/><Obs TIME_PERIOD="2023-Q2" OBS_VALUE="3.2"/><Obs TIME_PERIOD="2023-Q3" OBS_VALUE="3.0"/><Obs TIME_PERIOD="2023-Q4" OBS_VALUE="2.9"/></Series><Series age="Y15-74" freq="Q" geo="NL" sex="T" s_adj="SA" unit="PC_ACT"><Obs TIME_PERIOD="2010-Q1" OBS_VALUE="6.1"/><Obs TIME_PERIOD="2010-Q2" OBS_VALUE="6.1"/><Obs TIME_PERIOD="2010-Q3" OBS_VALUE="6.0"/><Obs TIME_PERIOD="2010-Q4" OBS_VALUE="6.0"/><Obs TIME_PERIOD="2011-Q1" OBS_VALUE="5.9"/><Obs TIME_PERIOD="2011-Q2" OBS_VALUE="5.9"/><Obs TIME_PERIOD="2011-Q3" OBS_VALUE="6.0"/><Obs TIME_PERIOD="2011-Q4" OBS_VALUE="6.3"/><Obs TIME_PERIOD="2012-Q1" OBS_VALUE="6.5"/><Obs TIME_PERIOD="2012-Q2" OBS_VALUE="6.7"/><Obs TIME_PERIOD="2012-Q3" OBS_VALUE="6.9"/><Obs TIME_PERIOD="2012-Q4" OBS_VALUE="7.3"/><Obs TIME_PERIOD="2013-Q1" OBS_VALUE="7.7"/><Obs TIME_PERIOD="2013-Q2" OBS_VALUE="8.1"/><Obs TIME_PERIOD="2013-Q3" OBS_VALUE="8.5"/><Obs TIME_PERIOD="2013-Q4" OBS_VALUE="8.6"/><Obs TIME_PERIOD="2014-Q1" OBS_VALUE="8.7"/><Obs TIME_PERIOD="2014-Q2" OBS_VALUE="8.5"/><Obs TIME_PERIOD="2014-Q3" OBS_VALUE="8.2"/><Obs TIME_PERIOD="2014-Q4" OBS_VALUE="8.2"/><Obs TIME_PERIOD="2015-Q1" OBS_VALUE="8.1"/><Obs TIME_PERIOD="2015-Q2" OBS_VALUE="7.9"/><Obs TIME_PERIOD="2015-Q3" OBS_VALUE="7.8"/><Obs TIME_PERIOD="2015-Q4" OBS_VALUE="7.7"/><Obs TIME_PERIOD="2016-Q1" OBS_VALUE="7.4"/><Obs TIME_PERIOD="2016-Q2" OBS_VALUE="7.3"/><Obs TIME_PERIOD="2016-Q3" OBS_VALUE="6.8"/><Obs TIME_PERIOD="2016-Q4" OBS_VALUE="6.5"/><Obs TIME_PERIOD="2017-Q1" OBS_VALUE="6.3"/><Obs TIME_PERIOD="2017-Q2" OBS_VALUE="6.1"/><Obs TIME_PERIOD="2017-Q3" OBS_VALUE="5.7"/><Obs TIME_PERIOD="2017-Q4" OBS_VALUE="5.4"/><Obs TIME_PERIOD="2018-Q1" OBS_VALUE="5.2"/><Obs TIME_PERIOD="2018-Q2" OBS_VALUE="5.0"/><Obs TIME_PERIOD="2018-Q3" OBS_VALUE="4.7"/><Obs TIME_PERIOD="2018-Q4" OBS_VALUE="4.6"/><Obs TIME_PERIOD="2019-Q1" OBS_VALUE="4.6"/><Obs TIME_PERIOD="2019-Q2" OBS_VALUE="4.4"/><Obs TIME_PERIOD="2019-Q3" OBS_VALUE="4.3"/><Obs TIME_PERIOD="2019-Q4" OBS_VALUE="4.4"/><Obs TIME_PERIOD="2020-Q1" OBS_VALUE="4.2"/><Obs TIME_PERIOD="2020-Q2" OBS_VALUE="4.9"/><Obs TIME_PERIOD="2020-Q3" OBS_VALUE="5.3"/><Obs TIME_PERIOD="2020-Q4" OBS_VALUE="5.0"/><Obs TIME_PERIOD="2021-Q1" OBS_VALUE="4.8"/><Obs TIME_PERIOD="2021-Q2" OBS_VALUE="4.4"/><Obs TIME_PERIOD="2021-Q3" OBS_VALUE="3.9"/><Obs TIME_PERIOD="2021-Q4" OBS_VALUE="3.8"/><Obs TIME_PERIOD="2022-Q1" OBS_VALUE="3.6"/><Obs TIME_PERIOD="2022-Q2" OBS_VALUE="3.4"/><Obs TIME_PERIOD="2022-Q3" OBS_VALUE="3.6"/><Obs TIME_PERIOD="2022-Q4" OBS_VALUE="3.5"/><Obs TIME_PERIOD="2023-Q1" OBS_VALUE="3.6"/><Obs TIME_PERIOD="2023-Q2" OBS_VALUE="3.6"/><Obs TIME_PERIOD="2023-Q3" OBS_VALUE="3.5"/><Obs TIME_PERIOD="2023-Q4" OBS_VALUE="3.5"/></Series><Series age="Y15-74" freq="Q" geo="NO" sex="T" s_adj="SA" unit="PC_ACT"><Obs TIME_PERIOD="2010-Q1" OBS_VALUE="4.1"/><Obs TIME_PERIOD="2010-Q2" OBS_VALUE="4.1"/><Obs TIME_PERIOD="2010-Q3" OBS_VALUE="3.8"/><Obs TIME_PERIOD="2010-Q4" OBS_VALUE="3.8"/><Obs TIME_PERIOD="2011-Q1" OBS_VALUE="3.5"/><Obs TIME_PERIOD="2011-Q2" OBS_VALUE="3.6"/><Obs TIME_PERIOD="2011-Q3" OBS_VALUE="3.5"/><Obs TIME_PERIOD="2011-Q4" OBS_VALUE="3.6"/><Obs TIME_PERIOD="2012-Q1" OBS_VALUE="3.5"/><Obs TIME_PERIOD="2012-Q2" OBS_VALUE="3.4"/><Obs TIME_PERIOD="2012-Q3" OBS_VALUE="3.3"/><Obs TIME_PERIOD="2012-Q4" OBS_VALUE="3.7"/><Obs TIME_PERIOD="2013-Q1" OBS_VALUE="3.9"/><Obs TIME_PERIOD="2013-Q2" OBS_VALUE="3.9"/><Obs TIME_PERIOD="2013-Q3" OBS_VALUE="3.9"/><Obs TIME_PERIOD="2013-Q4" OBS_VALUE="4.0"/><Obs TIME_PERIOD="2014-Q1" OBS_VALUE="3.8"/><Obs TIME_PERIOD="2014-Q2" OBS_VALUE="3.4"/><Obs TIME_PERIOD="2014-Q3" OBS_VALUE="3.9"/><Obs TIME_PERIOD="2014-Q4" OBS_VALUE="4.0"/><Obs TIME_PERIOD="2015-Q1" OBS_VALUE="4.5"/><Obs TIME_PERIOD="2015-Q2" OBS_VALUE="4.5"/><Obs TIME_PERIOD="2015-Q3" OBS_VALUE="4.7"/><Obs TIME_PERIOD="2015-Q4" OBS_VALUE="5.0"/><Obs TIME_PERIOD="2016-Q1" OBS_VALUE="5.1"/><Obs TIME_PERIOD="2016-Q2" OBS_VALUE="4.8"/><Obs TIME_PERIOD="2016-Q3" OBS_VALUE="4.9"/><Obs TIME_PERIOD="2016-Q4" OBS_VALUE="4.7"/><Obs TIME_PERIOD="2017-Q1" OBS_VALUE="4.5"/><Obs TIME_PERIOD="2017-Q2" OBS_VALUE="4.6"/><Obs TIME_PERIOD="2017-Q3" OBS_VALUE="4.2"/><Obs TIME_PERIOD="2017-Q4" OBS_VALUE="4.2"/><Obs TIME_PERIOD="2018-Q1" OBS_VALUE="4.1"/><Obs TIME_PERIOD="2018-Q2" OBS_VALUE="3.9"/><Obs TIME_PERIOD="2018-Q3" OBS_VALUE="4.1"/><Obs TIME_PERIOD="2018-Q4" OBS_VALUE="3.9"/><Obs TIME_PERIOD="2019-Q1" OBS_VALUE="4.0"/><Obs TIME_PERIOD="2019-Q2" OBS_VALUE="3.5"/><Obs TIME_PERIOD="2019-Q3" OBS_VALUE="3.9"/><Obs TIME_PERIOD="2019-Q4" OBS_VALUE="4.2"/><Obs TIME_PERIOD="2020-Q1" OBS_VALUE="3.8"/><Obs TIME_PERIOD="2020-Q2" OBS_VALUE="4.6"/><Obs TIME_PERIOD="2020-Q3" OBS_VALUE="5.4"/><Obs TIME_PERIOD="2020-Q4" OBS_VALUE="5.2"/><Obs TIME_PERIOD="2021-Q1" OBS_VALUE="4.9"/><Obs TIME_PERIOD="2021-Q2" OBS_VALUE="5.0"/><Obs TIME_PERIOD="2021-Q3" OBS_VALUE="4.1"/><Obs TIME_PERIOD="2021-Q4" OBS_VALUE="3.7"/><Obs TIME_PERIOD="2022-Q1" OBS_VALUE="3.3"/><Obs TIME_PERIOD="2022-Q2" OBS_VALUE="3.2"/><Obs TIME_PERIOD="2022-Q3" OBS_VALUE="3.2"/><Obs TIME_PERIOD="2022-Q4" OBS_VALUE="3.3"/><Obs TIME_PERIOD="2023-Q1" OBS_VALUE="3.7"/><Obs TIME_PERIOD="2023-Q2" OBS_VALUE="3.4"/><Obs TIME_PERIOD="2023-Q3" OBS_VALUE="3.5"/><Obs TIME_PERIOD="2023-Q4" OBS_VALUE="3.8"/></Series><Series age="Y15-74" freq="Q" geo="PL" sex="T" s_adj="SA" unit="PC_ACT"><Obs TIME_PERIOD="2010-Q1" OBS_VALUE="10.4" OBS_FLAG="b"/><Obs TIME_PERIOD="2010-Q2" OBS_VALUE="10.0"/><Obs TIME_PERIOD="2010-Q3" OBS_VALUE="9.8"/><Obs TIME_PERIOD="2010-Q4" OBS_VALUE="9.7"/><Obs TIME_PERIOD="2011-Q1" OBS_VALUE="9.8"/><Obs TIME_PERIOD="2011-Q2" OBS_VALUE="9.9"/><Obs TIME_PERIOD="2011-Q3" OBS_VALUE="10.0"/><Obs TIME_PERIOD="2011-Q4" OBS_VALUE="10.2"/><Obs TIME_PERIOD="2012-Q1" OBS_VALUE="10.2"/><Obs TIME_PERIOD="2012-Q2" OBS_VALUE="10.3"/><Obs TIME_PERIOD="2012-Q3" OBS_VALUE="10.6"/><Obs TIME_PERIOD="2012-Q4" OBS_VALUE="10.6"/><Obs TIME_PERIOD="2013-Q1" OBS_VALUE="10.8"/><Obs TIME_PERIOD="2013-Q2" OBS_VALUE="10.8"/><Obs TIME_PERIOD="2013-Q3" OBS_VALUE="10.6"/><Obs TIME_PERIOD="2013-Q4" OBS_VALUE="10.3"/><Obs TIME_PERIOD="2014-Q1" OBS_VALUE="10.0"/><Obs TIME_PERIOD="2014-Q2" OBS_VALUE="9.4"/><Obs TIME_PERIOD="2014-Q3" OBS_VALUE="8.8"/><Obs TIME_PERIOD="2014-Q4" OBS_VALUE="8.5"/><Obs TIME_PERIOD="2015-Q1" OBS_VALUE="8.2"/><Obs TIME_PERIOD="2015-Q2" OBS_VALUE="7.7"/><Obs TIME_PERIOD="2015-Q3" OBS_VALUE="7.5"/><Obs TIME_PERIOD="2015-Q4" OBS_VALUE="7.1"/><Obs TIME_PERIOD="2016-Q1" OBS_VALUE="6.8"/><Obs TIME_PERIOD="2016-Q2" OBS_VALUE="6.4"/><Obs TIME_PERIOD="2016-Q3" OBS_VALUE="6.1"/><Obs TIME_PERIOD="2016-Q4" OBS_VALUE="5.7"/><Obs TIME_PERIOD="2017-Q1" OBS_VALUE="5.3"/><Obs TIME_PERIOD="2017-Q2" OBS_VALUE="5.2"/><Obs TIME_PERIOD="2017-Q3" OBS_VALUE="4.7"/><Obs TIME_PERIOD="2017-Q4" OBS_VALUE="4.5"/><Obs TIME_PERIOD="2018-Q1" OBS_VALUE="4.2"/><Obs TIME_PERIOD="2018-Q2" OBS_VALUE="3.9"/><Obs TIME_PERIOD="2018-Q3" OBS_VALUE="3.8"/><Obs TIME_PERIOD="2018-Q4" OBS_VALUE="3.7"/><Obs TIME_PERIOD="2019-Q1" OBS_VALUE="3.8" OBS_FLAG="b"/><Obs TIME_PERIOD="2019-Q2" OBS_VALUE="3.3"/><Obs TIME_PERIOD="2019-Q3" OBS_VALUE="3.1"/><Obs TIME_PERIOD="2019-Q4" OBS_VALUE="3.0"/><Obs TIME_PERIOD="2020-Q1" OBS_VALUE="3.0"/><Obs TIME_PERIOD="2020-Q2" OBS_VALUE="3.2"/><Obs TIME_PERIOD="2020-Q3" OBS_VALUE="3.3"/><Obs TIME_PERIOD="2020-Q4" OBS_VALUE="3.3"/><Obs TIME_PERIOD="2021-Q1" OBS_VALUE="3.8"/><Obs TIME_PERIOD="2021-Q2" OBS_VALUE="3.6"/><Obs TIME_PERIOD="2021-Q3" OBS_VALUE="3.1"/><Obs TIME_PERIOD="2021-Q4" OBS_VALUE="3.0"/><Obs TIME_PERIOD="2022-Q1" OBS_VALUE="2.9"/><Obs TIME_PERIOD="2022-Q2" OBS_VALUE="2.8"/><Obs TIME_PERIOD="2022-Q3" OBS_VALUE="2.9"/><Obs TIME_PERIOD="2022-Q4" OBS_VALUE="2.8"/><Obs TIME_PERIOD="2023-Q1" OBS_VALUE="2.8"/><Obs TIME_PERIOD="2023-Q2" OBS_VALUE="2.8"/><Obs TIME_PERIOD="2023-Q3" OBS_VALUE="2.8"/><Obs TIME_PERIOD="2023-Q4" OBS_VALUE="2.9"/></Series><Series age="Y15-74" freq="Q" geo="PT" sex="T" s_adj="SA" unit="PC_ACT"><Obs TIME_PERIOD="2010-Q1" OBS_VALUE="12.1"/><Obs TIME_PERIOD="2010-Q2" OBS_VALUE="12.6"/><Obs TIME_PERIOD="2010-Q3" OBS_VALUE="13.0"/><Obs TIME_PERIOD="2010-Q4" OBS_VALUE="12.8"/><Obs TIME_PERIOD="2011-Q1" OBS_VALUE="12.8"/><Obs TIME_PERIOD="2011-Q2" OBS_VALUE="13.1"/><Obs TIME_PERIOD="2011-Q3" OBS_VALUE="13.5"/><Obs TIME_PERIOD="2011-Q4" OBS_VALUE="14.6"/><Obs TIME_PERIOD="2012-Q1" OBS_VALUE="15.4"/><Obs TIME_PERIOD="2012-Q2" OBS_VALUE="16.1"/><Obs TIME_PERIOD="2012-Q3" OBS_VALUE="17.1"/><Obs TIME_PERIOD="2012-Q4" OBS_VALUE="17.8"/><Obs TIME_PERIOD="2013-Q1" OBS_VALUE="18.2"/><Obs TIME_PERIOD="2013-Q2" OBS_VALUE="17.7"/><Obs TIME_PERIOD="2013-Q3" OBS_VALUE="16.8"/><Obs TIME_PERIOD="2013-Q4" OBS_VALUE="16.0"/><Obs TIME_PERIOD="2014-Q1" OBS_VALUE="15.4"/><Obs TIME_PERIOD="2014-Q2" OBS_VALUE="15.0"/><Obs TIME_PERIOD="2014-Q3" OBS_VALUE="14.1"/><Obs TIME_PERIOD="2014-Q4" OBS_VALUE="13.9"/><Obs TIME_PERIOD="2015-Q1" OBS_VALUE="13.9"/><Obs TIME_PERIOD="2015-Q2" OBS_VALUE="12.8"/><Obs TIME_PERIOD="2015-Q3" OBS_VALUE="12.7"/><Obs TIME_PERIOD="2015-Q4" OBS_VALUE="12.6"/><Obs TIME_PERIOD="2016-Q1" OBS_VALUE="12.4"/><Obs TIME_PERIOD="2016-Q2" OBS_VALUE="11.6"/><Obs TIME_PERIOD="2016-Q3" OBS_VALUE="11.2"/><Obs TIME_PERIOD="2016-Q4" OBS_VALUE="10.7"/><Obs TIME_PERIOD="2017-Q1" OBS_VALUE="10.0"/><Obs TIME_PERIOD="2017-Q2" OBS_VALUE="9.5"/><Obs TIME_PERIOD="2017-Q3" OBS_VALUE="9.0"/><Obs TIME_PERIOD="2017-Q4" OBS_VALUE="8.2"/><Obs TIME_PERIOD="2018-Q1" OBS_VALUE="7.7"/><Obs TIME_PERIOD="2018-Q2" OBS_VALUE="7.3"/><Obs TIME_PERIOD="2018-Q3" OBS_VALUE="7.2"/><Obs TIME_PERIOD="2018-Q4" OBS_VALUE="6.7"/><Obs TIME_PERIOD="2019-Q1" OBS_VALUE="6.6"/><Obs TIME_PERIOD="2019-Q2" OBS_VALUE="6.8"/><Obs TIME_PERIOD="2019-Q3" OBS_VALUE="6.6"/><Obs TIME_PERIOD="2019-Q4" OBS_VALUE="6.7"/><Obs TIME_PERIOD="2020-Q1" OBS_VALUE="6.4"/><Obs TIME_PERIOD="2020-Q2" OBS_VALUE="6.1"/><Obs TIME_PERIOD="2020-Q3" OBS_VALUE="8.2"/><Obs TIME_PERIOD="2020-Q4" OBS_VALUE="7.2"/><Obs TIME_PERIOD="2021-Q1" OBS_VALUE="6.9"/><Obs TIME_PERIOD="2021-Q2" OBS_VALUE="7.2"/><Obs TIME_PERIOD="2021-Q3" OBS_VALUE="6.5"/><Obs TIME_PERIOD="2021-Q4" OBS_VALUE="6.3"/><Obs TIME_PERIOD="2022-Q1" OBS_VALUE="5.7"/><Obs TIME_PERIOD="2022-Q2" OBS_VALUE="6.3"/><Obs TIME_PERIOD="2022-Q3" OBS_VALUE="6.3"/><Obs TIME_PERIOD="2022-Q4" OBS_VALUE="6.5"/><Obs TIME_PERIOD="2023-Q1" OBS_VALUE="6.8"/><Obs TIME_PERIOD="2023-Q2" OBS_VALUE="6.5"/><Obs TIME_PERIOD="2023-Q3" OBS_VALUE="6.4"/><Obs TIME_PERIOD="2023-Q4" OBS_VALUE="6.5"/></Series><Series age="Y15-74" freq="Q" geo="RO" sex="T" s_adj="SA" unit="PC_ACT"><Obs TIME_PERIOD="2010-Q1" OBS_VALUE="9.3"/><Obs TIME_PERIOD="2010-Q2" OBS_VALUE="9.0"/><Obs TIME_PERIOD="2010-Q3" OBS_VALUE="8.9"/><Obs TIME_PERIOD="2010-Q4" OBS_VALUE="8.7"/><Obs TIME_PERIOD="2011-Q1" OBS_VALUE="9.0"/><Obs TIME_PERIOD="2011-Q2" OBS_VALUE="9.1"/><Obs TIME_PERIOD="2011-Q3" OBS_VALUE="9.1"/><Obs TIME_PERIOD="2011-Q4" OBS_VALUE="9.2"/><Obs TIME_PERIOD="2012-Q1" OBS_VALUE="8.8"/><Obs TIME_PERIOD="2012-Q2" OBS_VALUE="8.7"/><Obs TIME_PERIOD="2012-Q3" OBS_VALUE="8.8"/><Obs TIME_PERIOD="2012-Q4" OBS_VALUE="8.7"/><Obs TIME_PERIOD="2013-Q1" OBS_VALUE="8.8"/><Obs TIME_PERIOD="2013-Q2" OBS_VALUE="9.2"/><Obs TIME_PERIOD="2013-Q3" OBS_VALUE="8.9"/><Obs TIME_PERIOD="2013-Q4" OBS_VALUE="8.9"/><Obs TIME_PERIOD="2014-Q1" OBS_VALUE="8.6"/><Obs TIME_PERIOD="2014-Q2" OBS_VALUE="8.7"/><Obs TIME_PERIOD="2014-Q3" OBS_VALUE="8.7"/><Obs TIME_PERIOD="2014-Q4" OBS_VALUE="8.6"/><Obs TIME_PERIOD="2015-Q1" OBS_VALUE="8.6"/><Obs TIME_PERIOD="2015-Q2" OBS_VALUE="8.3"/><Obs TIME_PERIOD="2015-Q3" OBS_VALUE="8.3"/><Obs TIME_PERIOD="2015-Q4" OBS_VALUE="8.2"/><Obs TIME_PERIOD="2016-Q1" OBS_VALUE="7.8"/><Obs TIME_PERIOD="2016-Q2" OBS_VALUE="7.2"/><Obs TIME_PERIOD="2016-Q3" OBS_VALUE="7.0"/><Obs TIME_PERIOD="2016-Q4" OBS_VALUE="6.7"/><Obs TIME_PERIOD="2017-Q1" OBS_VALUE="6.5"/><Obs TIME_PERIOD="2017-Q2" OBS_VALUE="6.0"/><Obs TIME_PERIOD="2017-Q3" OBS_VALUE="6.0"/><Obs TIME_PERIOD="2017-Q4" OBS_VALUE="5.9"/><Obs TIME_PERIOD="2018-Q1" OBS_VALUE="5.6"/><Obs TIME_PERIOD="2018-Q2" OBS_VALUE="5.3"/><Obs TIME_PERIOD="2018-Q3" OBS_VALUE="5.0"/><Obs TIME_PERIOD="2018-Q4" OBS_VALUE="5.0"/><Obs TIME_PERIOD="2019-Q1" OBS_VALUE="5.0"/><Obs TIME_PERIOD="2019-Q2" OBS_VALUE="5.0"/><Obs TIME_PERIOD="2019-Q3" OBS_VALUE="5.0"/><Obs TIME_PERIOD="2019-Q4" OBS_VALUE="4.8"/><Obs TIME_PERIOD="2020-Q1" OBS_VALUE="5.1"/><Obs TIME_PERIOD="2020-Q2" OBS_VALUE="6.6"/><Obs TIME_PERIOD="2020-Q3" OBS_VALUE="6.4"/><Obs TIME_PERIOD="2020-Q4" OBS_VALUE="6.1"/><Obs TIME_PERIOD="2021-Q1" OBS_VALUE="5.9"/><Obs TIME_PERIOD="2021-Q2" OBS_VALUE="5.5"/><Obs TIME_PERIOD="2021-Q3" OBS_VALUE="5.4"/><Obs TIME_PERIOD="2021-Q4" OBS_VALUE="5.6"/><Obs TIME_PERIOD="2022-Q1" OBS_VALUE="5.9"/><Obs TIME_PERIOD="2022-Q2" OBS_VALUE="5.5"/><Obs TIME_PERIOD="2022-Q3" OBS_VALUE="5.5"/><Obs TIME_PERIOD="2022-Q4" OBS_VALUE="5.6"/><Obs TIME_PERIOD="2023-Q1" OBS_VALUE="5.7"/><Obs TIME_PERIOD="2023-Q2" OBS_VALUE="5.7"/><Obs TIME_PERIOD="2023-Q3" OBS_VALUE="5.6"/><Obs TIME_PERIOD="2023-Q4" OBS_VALUE="5.6"/></Series><Series age="Y15-74" freq="Q" geo="RS" sex="T" s_adj="SA" unit="PC_ACT"><Obs TIME_PERIOD="2010-Q1" OBS_VALUE="20.7"/><Obs TIME_PERIOD="2010-Q2" OBS_VALUE="20.8"/><Obs TIME_PERIOD="2010-Q3" OBS_VALUE="21.3"/><Obs TIME_PERIOD="2010-Q4" OBS_VALUE="21.9"/><Obs TIME_PERIOD="2011-Q1" OBS_VALUE="23.1"/><Obs TIME_PERIOD="2011-Q2" OBS_VALUE="24.3"/><Obs TIME_PERIOD="2011-Q3" OBS_VALUE="26.0"/><Obs TIME_PERIOD="2011-Q4" OBS_VALUE="26.6"/><Obs TIME_PERIOD="2012-Q1" OBS_VALUE="26.6"/><Obs TIME_PERIOD="2012-Q2" OBS_VALUE="26.5"/><Obs TIME_PERIOD="2012-Q3" OBS_VALUE="26.0"/><Obs TIME_PERIOD="2012-Q4" OBS_VALUE="25.5"/><Obs TIME_PERIOD="2013-Q1" OBS_VALUE="25.4"/><Obs TIME_PERIOD="2013-Q2" OBS_VALUE="24.8"/><Obs TIME_PERIOD="2013-Q3" OBS_VALUE="23.6"/><Obs TIME_PERIOD="2013-Q4" OBS_VALUE="22.7"/><Obs TIME_PERIOD="2014-Q1" OBS_VALUE="21.8"/><Obs TIME_PERIOD="2014-Q2" OBS_VALUE="21.5"/><Obs TIME_PERIOD="2014-Q3" OBS_VALUE="20.1"/><Obs TIME_PERIOD="2014-Q4" OBS_VALUE="19.0"/><Obs TIME_PERIOD="2015-Q1" OBS_VALUE="19.2"/><Obs TIME_PERIOD="2015-Q2" OBS_VALUE="18.8"/><Obs TIME_PERIOD="2015-Q3" OBS_VALUE="18.8"/><Obs TIME_PERIOD="2015-Q4" OBS_VALUE="19.2"/><Obs TIME_PERIOD="2016-Q1" OBS_VALUE="18.6"/><Obs TIME_PERIOD="2016-Q2" OBS_VALUE="17.1"/><Obs TIME_PERIOD="2016-Q3" OBS_VALUE="15.8"/><Obs TIME_PERIOD="2016-Q4" OBS_VALUE="14.3"/><Obs TIME_PERIOD="2017-Q1" OBS_VALUE="14.5"/><Obs TIME_PERIOD="2017-Q2" OBS_VALUE="13.9"/><Obs TIME_PERIOD="2017-Q3" OBS_VALUE="14.7"/><Obs TIME_PERIOD="2017-Q4" OBS_VALUE="15.1"/><Obs TIME_PERIOD="2018-Q1" OBS_VALUE="14.7"/><Obs TIME_PERIOD="2018-Q2" OBS_VALUE="13.9"/><Obs TIME_PERIOD="2018-Q3" OBS_VALUE="13.2"/><Obs TIME_PERIOD="2018-Q4" OBS_VALUE="13.4"/><Obs TIME_PERIOD="2019-Q1" OBS_VALUE="12.1"/><Obs TIME_PERIOD="2019-Q2" OBS_VALUE="11.8"/><Obs TIME_PERIOD="2019-Q3" OBS_VALUE="10.9"/><Obs TIME_PERIOD="2019-Q4" OBS_VALUE="10.3"/><Obs TIME_PERIOD="2020-Q1" OBS_VALUE="9.8"/><Obs TIME_PERIOD="2020-Q2" OBS_VALUE="8.8"/><Obs TIME_PERIOD="2020-Q3" OBS_VALUE="10.3"/><Obs TIME_PERIOD="2020-Q4" OBS_VALUE="10.9"/><Obs TIME_PERIOD="2021-Q1" OBS_VALUE="11.7"/><Obs TIME_PERIOD="2021-Q2" OBS_VALUE="11.3"/><Obs TIME_PERIOD="2021-Q3" OBS_VALUE="10.9"/><Obs TIME_PERIOD="2021-Q4" OBS_VALUE="10.2"/><Obs TIME_PERIOD="2022-Q1" OBS_VALUE="10.0"/><Obs TIME_PERIOD="2022-Q2" OBS_VALUE="9.1"/><Obs TIME_PERIOD="2022-Q3" OBS_VALUE="9.4"/><Obs TIME_PERIOD="2022-Q4" OBS_VALUE="9.3"/><Obs TIME_PERIOD="2023-Q1" OBS_VALUE="9.4" OBS_FLAG="b"/><Obs TIME_PERIOD="2023-Q2" OBS_VALUE="9.7"/><Obs TIME_PERIOD="2023-Q3" OBS_VALUE="9.5"/><Obs TIME_PERIOD="2023-Q4" OBS_VALUE="9.3"/></Series><Series age="Y15-74" freq="Q" geo="SE" sex="T" s_adj="SA" unit="PC_ACT"><Obs TIME_PERIOD="2010-Q1" OBS_VALUE="9.2"/><Obs TIME_PERIOD="2010-Q2" OBS_VALUE="8.8"/><Obs TIME_PERIOD="2010-Q3" OBS_VALUE="8.7"/><Obs TIME_PERIOD="2010-Q4" OBS_VALUE="8.3"/><Obs TIME_PERIOD="2011-Q1" OBS_VALUE="8.1"/><Obs TIME_PERIOD="2011-Q2" OBS_VALUE="8.0"/><Obs TIME_PERIOD="2011-Q3" OBS_VALUE="7.8"/><Obs TIME_PERIOD="2011-Q4" OBS_VALUE="8.0"/><Obs TIME_PERIOD="2012-Q1" OBS_VALUE="7.9"/><Obs TIME_PERIOD="2012-Q2" OBS_VALUE="8.0"/><Obs TIME_PERIOD="2012-Q3" OBS_VALUE="8.3"/><Obs TIME_PERIOD="2012-Q4" OBS_VALUE="8.4"/><Obs TIME_PERIOD="2013-Q1" OBS_VALUE="8.3"/><Obs TIME_PERIOD="2013-Q2" OBS_VALUE="8.2"/><Obs TIME_PERIOD="2013-Q3" OBS_VALUE="8.2"/><Obs TIME_PERIOD="2013-Q4" OBS_VALUE="8.2"/><Obs TIME_PERIOD="2014-Q1" OBS_VALUE="8.2"/><Obs TIME_PERIOD="2014-Q2" OBS_VALUE="8.1"/><Obs TIME_PERIOD="2014-Q3" OBS_VALUE="8.0"/><Obs TIME_PERIOD="2014-Q4" OBS_VALUE="8.1"/><Obs TIME_PERIOD="2015-Q1" OBS_VALUE="7.9"/><Obs TIME_PERIOD="2015-Q2" OBS_VALUE="7.8"/><Obs TIME_PERIOD="2015-Q3" OBS_VALUE="7.3"/><Obs TIME_PERIOD="2015-Q4" OBS_VALUE="7.3"/><Obs TIME_PERIOD="2016-Q1" OBS_VALUE="7.3"/><Obs TIME_PERIOD="2016-Q2" OBS_VALUE="7.0"/><Obs TIME_PERIOD="2016-Q3" OBS_VALUE="7.0"/><Obs TIME_PERIOD="2016-Q4" OBS_VALUE="7.1"/><Obs TIME_PERIOD="2017-Q1" OBS_VALUE="6.9"/><Obs TIME_PERIOD="2017-Q2" OBS_VALUE="6.9"/><Obs TIME_PERIOD="2017-Q3" OBS_VALUE="6.9"/><Obs TIME_PERIOD="2017-Q4" OBS_VALUE="6.7"/><Obs TIME_PERIOD="2018-Q1" OBS_VALUE="6.4"/><Obs TIME_PERIOD="2018-Q2" OBS_VALUE="6.5"/><Obs TIME_PERIOD="2018-Q3" OBS_VALUE="6.6" OBS_FLAG="b"/><Obs TIME_PERIOD="2018-Q4" OBS_VALUE="6.6"/><Obs TIME_PERIOD="2019-Q1" OBS_VALUE="7.0"/><Obs TIME_PERIOD="2019-Q2" OBS_VALUE="6.7"/><Obs TIME_PERIOD="2019-Q3" OBS_VALUE="7.1"/><Obs TIME_PERIOD="2019-Q4" OBS_VALUE="7.1"/><Obs TIME_PERIOD="2020-Q1" OBS_VALUE="7.4"/><Obs TIME_PERIOD="2020-Q2" OBS_VALUE="8.6"/><Obs TIME_PERIOD="2020-Q3" OBS_VALUE="9.3"/><Obs TIME_PERIOD="2020-Q4" OBS_VALUE="8.9"/><Obs TIME_PERIOD="2021-Q1" OBS_VALUE="9.2"/><Obs TIME_PERIOD="2021-Q2" OBS_VALUE="9.2"/><Obs TIME_PERIOD="2021-Q3" OBS_VALUE="8.9"/><Obs TIME_PERIOD="2021-Q4" OBS_VALUE="8.2"/><Obs TIME_PERIOD="2022-Q1" OBS_VALUE="7.8"/><Obs TIME_PERIOD="2022-Q2" OBS_VALUE="7.7"/><Obs TIME_PERIOD="2022-Q3" OBS_VALUE="7.1"/><Obs TIME_PERIOD="2022-Q4" OBS_VALUE="7.4"/><Obs TIME_PERIOD="2023-Q1" OBS_VALUE="7.4"/><Obs TIME_PERIOD="2023-Q2" OBS_VALUE="7.5"/><Obs TIME_PERIOD="2023-Q3" OBS_VALUE="7.9"/><Obs TIME_PERIOD="2023-Q4" OBS_VALUE="8.0"/></Series><Series age="Y15-74" freq="Q" geo="SI" sex="T" s_adj="SA" unit="PC_ACT"><Obs TIME_PERIOD="2010-Q1" OBS_VALUE="6.8"/><Obs TIME_PERIOD="2010-Q2" OBS_VALUE="7.1"/><Obs TIME_PERIOD="2010-Q3" OBS_VALUE="7.2"/><Obs TIME_PERIOD="2010-Q4" OBS_VALUE="7.9"/><Obs TIME_PERIOD="2011-Q1" OBS_VALUE="8.1"/><Obs TIME_PERIOD="2011-Q2" OBS_VALUE="7.8"/><Obs TIME_PERIOD="2011-Q3" OBS_VALUE="8.1"/><Obs TIME_PERIOD="2011-Q4" OBS_VALUE="8.8"/><Obs TIME_PERIOD="2012-Q1" OBS_VALUE="8.1"/><Obs TIME_PERIOD="2012-Q2" OBS_VALUE="8.3"/><Obs TIME_PERIOD="2012-Q3" OBS_VALUE="9.5"/><Obs TIME_PERIOD="2012-Q4" OBS_VALUE="9.6"/><Obs TIME_PERIOD="2013-Q1" OBS_VALUE="10.6"/><Obs TIME_PERIOD="2013-Q2" OBS_VALUE="10.4"/><Obs TIME_PERIOD="2013-Q3" OBS_VALUE="9.8"/><Obs TIME_PERIOD="2013-Q4" OBS_VALUE="9.7"/><Obs TIME_PERIOD="2014-Q1" OBS_VALUE="10.2"/><Obs TIME_PERIOD="2014-Q2" OBS_VALUE="9.4"/><Obs TIME_PERIOD="2014-Q3" OBS_VALUE="9.6"/><Obs TIME_PERIOD="2014-Q4" OBS_VALUE="9.6"/><Obs TIME_PERIOD="2015-Q1" OBS_VALUE="9.3"/><Obs TIME_PERIOD="2015-Q2" OBS_VALUE="9.3"/><Obs TIME_PERIOD="2015-Q3" OBS_VALUE="8.9"/><Obs TIME_PERIOD="2015-Q4" OBS_VALUE="8.5"/><Obs TIME_PERIOD="2016-Q1" OBS_VALUE="8.4"/><Obs TIME_PERIOD="2016-Q2" OBS_VALUE="7.9"/><Obs TIME_PERIOD="2016-Q3" OBS_VALUE="7.6"/><Obs TIME_PERIOD="2016-Q4" OBS_VALUE="8.1"/><Obs TIME_PERIOD="2017-Q1" OBS_VALUE="7.4"/><Obs TIME_PERIOD="2017-Q2" OBS_VALUE="6.6"/><Obs TIME_PERIOD="2017-Q3" OBS_VALUE="6.5"/><Obs TIME_PERIOD="2017-Q4" OBS_VALUE="5.8"/><Obs TIME_PERIOD="2018-Q1" OBS_VALUE="5.6"/><Obs TIME_PERIOD="2018-Q2" OBS_VALUE="5.3"/><Obs TIME_PERIOD="2018-Q3" OBS_VALUE="5.1"/><Obs TIME_PERIOD="2018-Q4" OBS_VALUE="4.5"/><Obs TIME_PERIOD="2019-Q1" OBS_VALUE="4.5"/><Obs TIME_PERIOD="2019-Q2" OBS_VALUE="4.3"/><Obs TIME_PERIOD="2019-Q3" OBS_VALUE="4.8"/><Obs TIME_PERIOD="2019-Q4" OBS_VALUE="4.1"/><Obs TIME_PERIOD="2020-Q1" OBS_VALUE="4.3"/><Obs TIME_PERIOD="2020-Q2" OBS_VALUE="5.3"/><Obs TIME_PERIOD="2020-Q3" OBS_VALUE="5.1"/><Obs TIME_PERIOD="2020-Q4" OBS_VALUE="5.2"/><Obs TIME_PERIOD="2021-Q1" OBS_VALUE="5.4"/><Obs TIME_PERIOD="2021-Q2" OBS_VALUE="4.5"/><Obs TIME_PERIOD="2021-Q3" OBS_VALUE="4.5"/><Obs TIME_PERIOD="2021-Q4" OBS_VALUE="4.6"/><Obs TIME_PERIOD="2022-Q1" OBS_VALUE="4.1"/><Obs TIME_PERIOD="2022-Q2" OBS_VALUE="4.4"/><Obs TIME_PERIOD="2022-Q3" OBS_VALUE="4.0"/><Obs TIME_PERIOD="2022-Q4" OBS_VALUE="3.6"/><Obs TIME_PERIOD="2023-Q1" OBS_VALUE="3.6"/><Obs TIME_PERIOD="2023-Q2" OBS_VALUE="3.7"/><Obs TIME_PERIOD="2023-Q3" OBS_VALUE="3.8"/><Obs TIME_PERIOD="2023-Q4" OBS_VALUE="3.5"/></Series><Series age="Y15-74" freq="Q" geo="SK" sex="T" s_adj="SA" unit="PC_ACT"><Obs TIME_PERIOD="2010-Q1" OBS_VALUE="14.6"/><Obs TIME_PERIOD="2010-Q2" OBS_VALUE="14.5"/><Obs TIME_PERIOD="2010-Q3" OBS_VALUE="14.3"/><Obs TIME_PERIOD="2010-Q4" OBS_VALUE="13.8"/><Obs TIME_PERIOD="2011-Q1" OBS_VALUE="13.6" OBS_FLAG="b"/><Obs TIME_PERIOD="2011-Q2" OBS_VALUE="13.3"/><Obs TIME_PERIOD="2011-Q3" OBS_VALUE="13.3"/><Obs TIME_PERIOD="2011-Q4" OBS_VALUE="13.8"/><Obs TIME_PERIOD="2012-Q1" OBS_VALUE="13.8"/><Obs TIME_PERIOD="2012-Q2" OBS_VALUE="13.8"/><Obs TIME_PERIOD="2012-Q3" OBS_VALUE="13.9"/><Obs TIME_PERIOD="2012-Q4" OBS_VALUE="14.2"/><Obs TIME_PERIOD="2013-Q1" OBS_VALUE="14.3"/><Obs TIME_PERIOD="2013-Q2" OBS_VALUE="14.2"/><Obs TIME_PERIOD="2013-Q3" OBS_VALUE="14.1"/><Obs TIME_PERIOD="2013-Q4" OBS_VALUE="13.9"/><Obs TIME_PERIOD="2014-Q1" OBS_VALUE="13.7"/><Obs TIME_PERIOD="2014-Q2" OBS_VALUE="13.3"/><Obs TIME_PERIOD="2014-Q3" OBS_VALUE="12.9"/><Obs TIME_PERIOD="2014-Q4" OBS_VALUE="12.4"/><Obs TIME_PERIOD="2015-Q1" OBS_VALUE="12.2"/><Obs TIME_PERIOD="2015-Q2" OBS_VALUE="11.5"/><Obs TIME_PERIOD="2015-Q3" OBS_VALUE="11.3"/><Obs TIME_PERIOD="2015-Q4" OBS_VALUE="10.8"/><Obs TIME_PERIOD="2016-Q1" OBS_VALUE="10.3"/><Obs TIME_PERIOD="2016-Q2" OBS_VALUE="9.9"/><Obs TIME_PERIOD="2016-Q3" OBS_VALUE="9.5"/><Obs TIME_PERIOD="2016-Q4" OBS_VALUE="9.0"/><Obs TIME_PERIOD="2017-Q1" OBS_VALUE="8.6"/><Obs TIME_PERIOD="2017-Q2" OBS_VALUE="8.2"/><Obs TIME_PERIOD="2017-Q3" OBS_VALUE="7.8"/><Obs TIME_PERIOD="2017-Q4" OBS_VALUE="7.6"/><Obs TIME_PERIOD="2018-Q1" OBS_VALUE="7.1"/><Obs TIME_PERIOD="2018-Q2" OBS_VALUE="6.7"/><Obs TIME_PERIOD="2018-Q3" OBS_VALUE="6.2"/><Obs TIME_PERIOD="2018-Q4" OBS_VALUE="6.0"/><Obs TIME_PERIOD="2019-Q1" OBS_VALUE="5.8"/><Obs TIME_PERIOD="2019-Q2" OBS_VALUE="5.7"/><Obs TIME_PERIOD="2019-Q3" OBS_VALUE="5.7"/><Obs TIME_PERIOD="2019-Q4" OBS_VALUE="5.7"/><Obs TIME_PERIOD="2020-Q1" OBS_VALUE="6.0"/><Obs TIME_PERIOD="2020-Q2" OBS_VALUE="6.5"/><Obs TIME_PERIOD="2020-Q3" OBS_VALUE="7.0"/><Obs TIME_PERIOD="2020-Q4" OBS_VALUE="7.0"/><Obs TIME_PERIOD="2021-Q1" OBS_VALUE="7.2"/><Obs TIME_PERIOD="2021-Q2" OBS_VALUE="6.9"/><Obs TIME_PERIOD="2021-Q3" OBS_VALUE="6.7"/><Obs TIME_PERIOD="2021-Q4" OBS_VALUE="6.5"/><Obs TIME_PERIOD="2022-Q1" OBS_VALUE="6.4"/><Obs TIME_PERIOD="2022-Q2" OBS_VALUE="6.3"/><Obs TIME_PERIOD="2022-Q3" OBS_VALUE="6.0"/><Obs TIME_PERIOD="2022-Q4" OBS_VALUE="6.0"/><Obs TIME_PERIOD="2023-Q1" OBS_VALUE="6.1"/><Obs TIME_PERIOD="2023-Q2" OBS_VALUE="5.9"/><Obs TIME_PERIOD="2023-Q3" OBS_VALUE="5.8"/><Obs TIME_PERIOD="2023-Q4" OBS_VALUE="5.6"/></Series><Series age="Y15-74" freq="Q" geo="TR" sex="T" s_adj="SA" unit="PC_ACT"><Obs TIME_PERIOD="2010-Q1" OBS_VALUE="11.7"/><Obs TIME_PERIOD="2010-Q2" OBS_VALUE="10.7"/><Obs TIME_PERIOD="2010-Q3" OBS_VALUE="10.4"/><Obs TIME_PERIOD="2010-Q4" OBS_VALUE="9.9"/><Obs TIME_PERIOD="2011-Q1" OBS_VALUE="9.4"/><Obs TIME_PERIOD="2011-Q2" OBS_VALUE="9.3"/><Obs TIME_PERIOD="2011-Q3" OBS_VALUE="8.5"/><Obs TIME_PERIOD="2011-Q4" OBS_VALUE="8.2"/><Obs TIME_PERIOD="2012-Q1" OBS_VALUE="8.4"/><Obs TIME_PERIOD="2012-Q2" OBS_VALUE="8.0"/><Obs TIME_PERIOD="2012-Q3" OBS_VALUE="7.9"/><Obs TIME_PERIOD="2012-Q4" OBS_VALUE="8.4"/><Obs TIME_PERIOD="2013-Q1" OBS_VALUE="8.6"/><Obs TIME_PERIOD="2013-Q2" OBS_VALUE="8.7"/><Obs TIME_PERIOD="2013-Q3" OBS_VALUE="8.9"/><Obs TIME_PERIOD="2013-Q4" OBS_VALUE="8.9"/><Obs TIME_PERIOD="2014-Q1" OBS_VALUE="9.3" OBS_FLAG="b"/><Obs TIME_PERIOD="2014-Q2" OBS_VALUE="9.6"/><Obs TIME_PERIOD="2014-Q3" OBS_VALUE="10.2"/><Obs TIME_PERIOD="2014-Q4" OBS_VALUE="10.7"/><Obs TIME_PERIOD="2015-Q1" OBS_VALUE="10.3"/><Obs TIME_PERIOD="2015-Q2" OBS_VALUE="10.2"/><Obs TIME_PERIOD="2015-Q3" OBS_VALUE="10.2"/><Obs TIME_PERIOD="2015-Q4" OBS_VALUE="10.4"/><Obs TIME_PERIOD="2016-Q1" OBS_VALUE="10.0"/><Obs TIME_PERIOD="2016-Q2" OBS_VALUE="10.2"/><Obs TIME_PERIOD="2016-Q3" OBS_VALUE="11.3"/><Obs TIME_PERIOD="2016-Q4" OBS_VALUE="11.9"/><Obs TIME_PERIOD="2017-Q1" OBS_VALUE="11.7"/><Obs TIME_PERIOD="2017-Q2" OBS_VALUE="11.0"/><Obs TIME_PERIOD="2017-Q3" OBS_VALUE="10.5"/><Obs TIME_PERIOD="2017-Q4" OBS_VALUE="10.2"/><Obs TIME_PERIOD="2018-Q1" OBS_VALUE="9.9"/><Obs TIME_PERIOD="2018-Q2" OBS_VALUE="10.4"/><Obs TIME_PERIOD="2018-Q3" OBS_VALUE="11.2"/><Obs TIME_PERIOD="2018-Q4" OBS_VALUE="12.3"/><Obs TIME_PERIOD="2019-Q1" OBS_VALUE="13.7"/><Obs TIME_PERIOD="2019-Q2" OBS_VALUE="13.7"/><Obs TIME_PERIOD="2019-Q3" OBS_VALUE="14.1"/><Obs TIME_PERIOD="2019-Q4" OBS_VALUE="13.3"/><Obs TIME_PERIOD="2020-Q1" OBS_VALUE="12.7"/><Obs TIME_PERIOD="2020-Q2" OBS_VALUE="13.6"/><Obs TIME_PERIOD="2020-Q3" OBS_VALUE="13.3"/><Obs TIME_PERIOD="2020-Q4" OBS_VALUE="12.9"/><Obs TIME_PERIOD="2021-Q1" OBS_VALUE="12.7" OBS_FLAG="b"/><Obs TIME_PERIOD="2021-Q2" OBS_VALUE="12.5"/><Obs TIME_PERIOD="2021-Q3" OBS_VALUE="11.8"/><Obs TIME_PERIOD="2021-Q4" OBS_VALUE="11.1"/><Obs TIME_PERIOD="2022-Q1" OBS_VALUE="10.9"/><Obs TIME_PERIOD="2022-Q2" OBS_VALUE="10.8"/><Obs TIME_PERIOD="2022-Q3" OBS_VALUE="10.1"/><Obs TIME_PERIOD="2022-Q4" OBS_VALUE="10.2"/><Obs TIME_PERIOD="2023-Q1" OBS_VALUE="9.9"/><Obs TIME_PERIOD="2023-Q2" OBS_VALUE="9.8"/><Obs TIME_PERIOD="2023-Q3" OBS_VALUE="9.3"/><Obs TIME_PERIOD="2023-Q4" OBS_VALUE="8.8"/></Series></m:DataSet></m:StructureSpecificData>